[{"id":"bp1","cn":"Pipevine Swallowtail","sn":"Battus philenor","fam":"Papilionidae","st":"rare","desc":"Iridescent blue-black swallowtail. Stray/rare colonist in SoCal — no native Aristolochia. Toxic; model for a Batesian mimicry complex. Established only where pipevine is cultivated.","fm":{"Wingspan":"3–3.5 in","Upperside":"Iridescent blue-black; single row of pale hindwing spots","Underside":"Vivid orange submarginal spots on iridescent blue hindwing","Flight Period":"Mar–Oct; 2–3 broods","Host Plants":"Aristolochia californica","Habitat":"Riparian woodland, foothill canyons"},"mo":[3,4,5,6,7,8,9],"pk":[4,5],"hp":"Aristolochia californica","elev":"low,foot"},{"id":"pa1","cn":"Anise Swallowtail","sn":"Papilio zelicaon","fam":"Papilionidae","st":"common","desc":"Widespread adaptable swallowtail at home in hilltop chaparral and suburban fennel gardens alike.","fm":{"Wingspan":"2–3 in","Upperside":"Black with broad yellow band; blue/orange hindwing eyespot","Underside":"Yellow spots may be cream or orange-tinged","Flight Period":"Mar–Oct; 2–3 broods","Host Plants":"Apiaceae — fennel, Lomatium, Angelica","Habitat":"Hilltops, chaparral, coastal sage, gardens"},"mo":[3,4,5,6,7,8,9,10],"pk":[],"hp":"Apiaceae — fennel, Lomatium, Angelica","elev":"wide"},{"id":"pi1","cn":"Indra Swallowtail","sn":"Papilio indra","fam":"Papilionidae","st":"rare","desc":"Dark, short-tailed swallowtail of arid rocky habitats. LA County populations restricted to upper desert canyons.","fm":{"Wingspan":"2–3 in","Upperside":"Black with reduced cream bands; short stubby tails","Underside":"Blue and orange hindwing spots on dark ground","Flight Period":"Mar–May; single brood","Host Plants":"Apiaceae — Lomatium, Pteryxia","Habitat":"Rocky canyon walls, arid hillsides above 3,500'"},"mo":[3,4,5],"pk":[],"hp":"Apiaceae — Lomatium, Pteryxia","elev":"mid,high"},{"id":"pr1","cn":"Western Tiger Swallowtail","sn":"Papilio rutulus","fam":"Papilionidae","st":"common","desc":"Iconic large yellow swallowtail of western riparian corridors. Strong, sailing flight.","fm":{"Wingspan":"3–4 in","Upperside":"Bright yellow with bold black tiger stripes; single tail","Underside":"Blue and orange marginal hindwing spots","Flight Period":"Feb–Oct; multiple broods","Host Plants":"Platanus, Salix, Populus","Habitat":"Riparian canyons, parks, mountain streams"},"mo":[2,3,4,5,6,7,8,9,10],"pk":[],"hp":"Platanus, Salix, Populus","elev":"low,foot,mid"},{"id":"pe1","cn":"Pale Swallowtail","sn":"Papilio eurymedon","fam":"Papilionidae","st":"uncommon","desc":"Cream-white swallowtail replacing the Tiger at higher elevations in the San Gabriel Mountains.","fm":{"Wingspan":"2.5–3.5 in","Upperside":"Cream-white with black tiger stripes; blue/orange marginal spots","Underside":"Cream with subdued markings","Flight Period":"Apr–Jul; single brood","Host Plants":"Ceanothus, Rhamnus, Prunus","Habitat":"Mountain canyons, chaparral, oak-pine above 3,000'"},"mo":[4,5,6,7],"pk":[],"hp":"Ceanothus, Rhamnus, Prunus","elev":"foot,mid"},{"id":"pm1","cn":"Two-tailed Swallowtail","sn":"Papilio multicaudata","fam":"Papilionidae","st":"rare","desc":"Largest western swallowtail — two tails per hindwing diagnostic. Rare stray to LA County from desert ranges.","fm":{"Wingspan":"4–6 in","Upperside":"Yellow with narrow stripes; 2 tails per hindwing","Underside":"Yellow with blue marginal crescents","Flight Period":"May–Sep","Host Plants":"Fraxinus, Prunus, Ligustrum","Habitat":"Desert riparian; vagrant to coastal LA"},"mo":[5,6,7,8,9],"pk":[],"hp":"Fraxinus, Prunus, Ligustrum","elev":"foot,mid"},{"id":"pi2","cn":"Cabbage White","sn":"Pieris rapae","fam":"Pieridae","st":"common","desc":"Introduced. The most abundant butterfly in urban LA.","fm":{"Wingspan":"1.5–2 in","Upperside":"White with black forewing tips; 1 spot (♂) or 2 (♀)","Underside":"Pale greenish-yellow hindwing","Flight Period":"Year-round","Host Plants":"Brassicaceae — mustards, broccoli, nasturtium","Habitat":"Ubiquitous"},"mo":[1,2,3,4,5,6,7,8,9,10,11,12],"pk":[3,4,5,9,10],"hp":"Brassicaceae — mustards, broccoli, nasturtium","elev":"wide"},{"id":"pp1","cn":"Checkered White","sn":"Pontia protodice","fam":"Pieridae","st":"common","desc":"Boldly checkered white of weedy habitats. More marked than Cabbage White.","fm":{"Wingspan":"1.5–2 in","Upperside":"White with heavy charcoal checkering; ♀ darker","Underside":"Olive-green vein markings on hindwing","Flight Period":"Year-round; peaks spring/fall","Host Plants":"Brassicaceae — wild mustards, peppergrass","Habitat":"Weedy fields, roadsides, agricultural edges"},"mo":[1,2,3,4,5,6,7,8,9,10,11,12],"pk":[],"hp":"Brassicaceae: mustards, Sisymbrium spp.","elev":"low,foot"},{"id":"ps1","cn":"Spring White","sn":"Pontia sisymbrii","fam":"Pieridae","st":"uncommon","desc":"Delicate, lightly marked white of montane chaparral. Single-brooded spring flier.","fm":{"Wingspan":"1–1.5 in","Upperside":"White with light gray-green vein-end markings","Underside":"Hindwing veins yellow-green outlined","Flight Period":"Feb–May; single brood","Host Plants":"Brassicaceae — Descurainia, Arabis","Habitat":"Chaparral, rocky hillsides, foothill washes"},"mo":[2,3,4,5],"pk":[],"hp":"Brassicaceae — Descurainia, Arabis","elev":"foot,mid"},{"id":"as1","cn":"Sara Orangetip","sn":"Anthocharis sara","fam":"Pieridae","st":"common","desc":"Spring ephemeral — vivid orange wingtips signal wildflower season.","fm":{"Wingspan":"1–1.5 in","Upperside":"White with vivid orange forewing tips (♂); reduced (♀)","Underside":"Hindwing marbled green-brown (cryptic)","Flight Period":"Feb–May; single brood","Host Plants":"Brassicaceae — Sisymbrium, Arabis","Habitat":"Chaparral, coastal sage, hillside meadows"},"mo":[2,3,4,5],"pk":[],"hp":"Brassicaceae — Sisymbrium, Arabis","elev":"foot,mid"},{"id":"ag1","cn":"Gray Marble","sn":"Anthocharis lanceolata","fam":"Pieridae","st":"uncommon","desc":"Small, subtly marbled white. Distinguished from Sara Orangetip by lack of orange tips.","fm":{"Wingspan":"1–1.5 in","Upperside":"White; gray-tipped forewing apex (no orange)","Underside":"Finely marbled gray-green; no orange","Flight Period":"Mar–May; single brood","Host Plants":"Brassicaceae — Arabis, Streptanthus","Habitat":"Rocky hillsides, chaparral, canyon walls"},"mo":[3,4,5],"pk":[],"hp":"Brassicaceae — Arabis, Streptanthus","elev":"foot,mid"},{"id":"ce1","cn":"Orange Sulphur","sn":"Colias eurytheme","fam":"Pieridae","st":"common","desc":"Abundant golden-orange butterfly of every alfalfa field and park lawn.","fm":{"Wingspan":"1.5–2 in","Upperside":"Orange with wide black borders; pink fringes","Underside":"Yellow-green with silver cell spot ringed in pink","Flight Period":"Year-round; peaks spring/fall","Host Plants":"Fabaceae — alfalfa, clover, vetches","Habitat":"Agricultural fields, lawns, parks"},"mo":[1,2,3,4,5,6,7,8,9,10,11,12],"pk":[],"hp":"Fabaceae: alfalfa (Medicago sativa), clovers (Trifolium), vetches","elev":"low,foot"},{"id":"ze1","cn":"California Dogface","sn":"Zerene eurydice","fam":"Pieridae","st":"uncommon","desc":"California state butterfly. Male's forewing pattern resembles a poodle face in silhouette.","fm":{"Wingspan":"2–2.5 in","Upperside":"♂: yellow with purple-black \"dogface\" pattern. ♀: plain yellow.","Underside":"Yellow to greenish; small pink cell spot","Flight Period":"Apr–Oct; 1–2 broods","Host Plants":"Amorpha californica (false indigo)","Habitat":"Foothill chaparral with false indigo"},"mo":[4,5,6,7,8],"pk":[5,6,7],"hp":"Amorpha californica (false indigo)","elev":"foot,mid"},{"id":"ni1","cn":"Dainty Sulphur","sn":"Nathalis iole","fam":"Pieridae","st":"uncommon","desc":"Smallest NA pierid. Dainty, low flight through weedy lots.","fm":{"Wingspan":"⅔ in–1 in (smallest NA pierid)","Upperside":"Yellow with black forewing tips","Underside":"Winter form darker, heavily dusted","Flight Period":"Year-round; peaks spring/fall","Host Plants":"Asteraceae — Bidens, Dyssodia","Habitat":"Weedy lots, roadsides, desert edges"},"mo":[1,2,3,4,5,6,7,8,9,10,11,12],"pk":[],"hp":"Asteraceae — Bidens, Dyssodia","elev":"low,foot"},{"id":"ps2","cn":"Cloudless Sulphur","sn":"Phoebis sennae","fam":"Pieridae","st":"common","desc":"Large bright Neotropical wanderer. Colonizes SoCal in warm years.","fm":{"Wingspan":"2–3 in","Upperside":"♂: unmarked bright yellow. ♀: paler.","Underside":"Yellow-green; reddish cell spot","Flight Period":"Jun–Nov; immigration-dependent","Host Plants":"Fabaceae — Cassia, Senna","Habitat":"Gardens during immigration years"},"mo":[6,7,8,9,10,11],"pk":[],"hp":"Fabaceae: Senna spp., Cassia spp.","elev":"low"},{"id":"lh1","cn":"Purplish Copper","sn":"Lycaena helloides","fam":"Lycaenidae","st":"uncommon","desc":"Wetland copper with purple iridescence on males.","fm":{"Wingspan":"1–1.5 in","Upperside":"♂: dark with purple sheen/orange band. ♀: orange, heavy spotting.","Underside":"Tan with black spots; orange submarginal band","Flight Period":"Mar–Oct; 2–3 broods","Host Plants":"Rumex, Polygonum (docks, knotweeds)","Habitat":"Wet meadows, stream margins"},"mo":[3,4,5,6,7,8,9,10],"pk":[],"hp":"Rumex, Polygonum (docks, knotweeds)","elev":"low,foot,mid"},{"id":"sm1","cn":"Gray Hairstreak","sn":"Strymon melinus","fam":"Lycaenidae","st":"common","desc":"Most widespread NA hairstreak. Subtle gray with orange-and-black hindwing spots.","fm":{"Wingspan":"¾ in–1.5 in","Upperside":"Blue-gray (♂); darker gray (♀)","Underside":"Pale gray with white-edged postmedian line; orange spots","Flight Period":"Year-round; 3+ broods","Host Plants":"Polyphagous — Fabaceae, Malvaceae, Rosaceae","Habitat":"Open areas, gardens, chaparral"},"mo":[1,2,3,4,5,6,7,8,9,10,11,12],"pk":[],"hp":"Polyphagous — Fabaceae, Malvaceae, Rosaceae","elev":"foot,mid"},{"id":"ah1","cn":"Great Purple Hairstreak","sn":"Atlides halesus","fam":"Lycaenidae","st":"uncommon","desc":"Brilliant iridescent blue. Perches high in oak canopy near mistletoe.","fm":{"Wingspan":"1–1.5 in","Upperside":"Brilliant iridescent blue; red basal spots","Underside":"Black with red-orange basal spots; blue-green highlights","Flight Period":"Mar–Oct; 2 broods","Host Plants":"Phoradendron (mistletoe) on oaks","Habitat":"Oak woodland, riparian with mistletoe"},"mo":[3,4,5,6,7,8,9,10],"pk":[],"hp":"Phoradendron (mistletoe) on oaks","elev":"low,foot"},{"id":"sc1","cn":"California Hairstreak","sn":"Satyrium californica","fam":"Lycaenidae","st":"uncommon","desc":"Warm brown hairstreak with orange hindwing crescents.","fm":{"Wingspan":"1 in","Upperside":"Brown with faint orange marginal spots","Underside":"Brown-gray; black spot row edged white; orange crescents","Flight Period":"May–Jul; single brood","Host Plants":"Ceanothus, Cercocarpus, Prunus","Habitat":"Chaparral, oak woodland"},"mo":[5,6,7],"pk":[],"hp":"Ceanothus, Cercocarpus, Prunus","elev":"foot,mid"},{"id":"sh1","cn":"Hedgerow Hairstreak","sn":"Satyrium saepium","fam":"Lycaenidae","st":"uncommon","desc":"Golden-brown, associated with Ceanothus. Often hilltopping.","fm":{"Wingspan":"¾ in–1 in","Upperside":"Warm golden-brown","Underside":"Golden-brown with postmedian line","Flight Period":"May–Jul; single brood","Host Plants":"Ceanothus spp.","Habitat":"Chaparral summits"},"mo":[5,6,7],"pk":[],"hp":"Ceanothus spp.","elev":"foot,mid"},{"id":"cd1","cn":"Bramble Hairstreak","sn":"Callophrys dumetorum","fam":"Lycaenidae","st":"uncommon","desc":"Tiny, dazzling emerald green underside when fresh.","fm":{"Wingspan":"⅔ in–1 in","Upperside":"Brown (rarely seen)","Underside":"Bright emerald green fading to olive; white line","Flight Period":"Mar–May; single brood","Host Plants":"Lotus scoparius, Eriogonum fasciculatum","Habitat":"Coastal sage, chaparral, foothill canyons"},"mo":[3,4,5],"pk":[],"hp":"Lotus scoparius, Eriogonum fasciculatum","elev":"foot,mid"},{"id":"be1","cn":"Western Pygmy Blue","sn":"Brephidium exilis","fam":"Lycaenidae","st":"common","desc":"Smallest NA butterfly — wingspan barely ½ in.","fm":{"Wingspan":"½ in–⅔ in (smallest NA butterfly)","Upperside":"Copper-brown with blue basal wash","Underside":"Brown base, white outer; 3 hindwing eyespots","Flight Period":"Year-round","Host Plants":"Chenopodiaceae — Suaeda, Atriplex","Habitat":"Salt marshes, alkali flats, weedy lots"},"mo":[1,2,3,4,5,6,7,8,9,10,11,12],"pk":[],"hp":"Chenopodiaceae — Suaeda, Atriplex","elev":"coast"},{"id":"lm1","cn":"Marine Blue","sn":"Leptotes marina","fam":"Lycaenidae","st":"common","desc":"Tiny iridescent blue in constant low flight through urban gardens.","fm":{"Wingspan":"⅔ in–1 in","Upperside":"Lavender-blue (♂); brown with blue basal (♀)","Underside":"Pale with brown/white banding; 2 eyespots","Flight Period":"Mar–Nov; multiple broods","Host Plants":"Plumbago, Medicago, Astragalus","Habitat":"Urban gardens, weedy lots, coastal scrub"},"mo":[3,4,5,6,7,8,9,10,11],"pk":[],"hp":"Plumbago, Medicago, Astragalus","elev":"coast"},{"id":"ce2","cn":"Echo Azure","sn":"Celastrina echo","fam":"Lycaenidae","st":"common","desc":"Spring-flying pale blue of riparian and chaparral. Among first blues each year.","fm":{"Wingspan":"¾ in–1 in","Upperside":"Pale silvery-blue with narrow dark margin","Underside":"Pale gray with faint dark spots; no orange","Flight Period":"Feb–May; single brood","Host Plants":"Ceanothus, Rhamnus, Cornus — flowers/buds","Habitat":"Riparian woodland, chaparral, oak woodland"},"mo":[2,3,4,5],"pk":[],"hp":"Ceanothus, Rhamnus, Cornus — flowers/buds","elev":"foot,mid"},{"id":"gl1","cn":"Silvery Blue","sn":"Glaucopsyche lygdamus","fam":"Lycaenidae","st":"uncommon","desc":"Spring-flying blue of open woodland. Prominent round black spots below.","fm":{"Wingspan":"1–1.5 in","Upperside":"Silvery-blue (♂); brown with blue basal (♀)","Underside":"Gray with single row of prominent round black spots","Flight Period":"Mar–Jun; single brood","Host Plants":"Lupinus, Astragalus, Lathyrus, Vicia","Habitat":"Open woodland, meadow edges"},"mo":[3,4,5,6],"pk":[],"hp":"Lupinus, Astragalus, Lathyrus, Vicia","elev":"low,foot"},{"id":"eb1","cn":"Square-spotted Blue","sn":"Euphilotes battoides","fam":"Lycaenidae","st":"uncommon","desc":"Buckwheat specialist. Squarish metallic marginal spots diagnostic.","fm":{"Wingspan":"⅔ in–1 in","Upperside":"Blue (♂) or brown (♀)","Underside":"Orange band with squarish metallic spots","Flight Period":"May–Aug; single brood, sync with buckwheat","Host Plants":"Eriogonum flowers (oligolectic)","Habitat":"Rocky hillsides with Eriogonum"},"mo":[5,6,7,8],"pk":[],"hp":"Eriogonum flowers (oligolectic)","elev":"foot,mid"},{"id":"dp1","cn":"Monarch","sn":"Danaus plexippus","fam":"Nymphalidae","st":"common","desc":"Western migratory Monarch — IUCN Endangered, USFWS candidate. LA County hosts coastal winter roosts. Population collapsed >95%.","fm":{"Wingspan":"3.5–4 in","Upperside":"Deep orange with black veins; white spots in margins","Underside":"Paler; hindwing golden-brown","Flight Period":"Year-round; roosts Oct–Feb; breeding Mar–Nov","Host Plants":"Asclepias — obligate","Habitat":"Coastal roost groves; milkweed gardens"},"mo":[1,2,3,4,5,6,7,8,9,10,11,12],"pk":[9,10,11],"hp":"Apocynaceae: Asclepias spp. (milkweeds)","elev":"wide"},{"id":"dg1","cn":"Queen","sn":"Danaus gilippus","fam":"Nymphalidae","st":"uncommon","desc":"Monarch's smaller, darker relative. Desert-edge. Milkweed-dependent.","fm":{"Wingspan":"2.5–3 in","Upperside":"Rich chestnut-brown; white forewing spots; no black veining","Underside":"Chestnut with veins outlined in black","Flight Period":"Mar–Nov; multiple broods","Host Plants":"Asclepias subulata, A. erosa","Habitat":"Desert washes, arid scrub"},"mo":[3,4,5,6,7,8,9,10,11],"pk":[],"hp":"Apocynaceae: Asclepias, Funastrum (climbing milkweed)","elev":"low,foot"},{"id":"dv1","cn":"Gulf Fritillary","sn":"Dione vanillae","fam":"Nymphalidae","st":"common","desc":"Brilliant orange with extraordinary metallic silver underside. Abundant on Passiflora.","fm":{"Wingspan":"2.5–3 in","Upperside":"Bright orange; 3 white-centered black forewing spots","Underside":"Large metallic silver spots (spectacular)","Flight Period":"Year-round; peaks spring/fall","Host Plants":"Passiflora (passionvine)","Habitat":"Urban gardens with passionflower"},"mo":[1,2,3,4,5,6,7,8,9,10,11,12],"pk":[7,8,9,10],"hp":"Passifloraceae: Passiflora spp. (passionflower vines)","elev":"low"},{"id":"ec1","cn":"Variegated Fritillary","sn":"Euptoieta claudia","fam":"Nymphalidae","st":"uncommon","desc":"Flat-winged, low-flying tawny fritillary. No metallic silver below.","fm":{"Wingspan":"2–2.5 in","Upperside":"Tawny with dark zigzag lines; no silver","Underside":"Mottled brown/cream; dark median band","Flight Period":"Mar–Nov; 2–3 broods","Host Plants":"Passifloraceae, Violaceae, Plantaginaceae","Habitat":"Open fields, roadsides"},"mo":[3,4,5,6,7,8,9,10,11],"pk":[],"hp":"Passifloraceae, Violaceae, Plantaginaceae","elev":"low,foot"},{"id":"vc1","cn":"Painted Lady","sn":"Vanessa cardui","fam":"Nymphalidae","st":"common","desc":"World's most widespread butterfly. Spectacular northward irruptions — 2019 triggered billions of migrants through LA.","fm":{"Wingspan":"2–3 in","Upperside":"Orange-brown; white forewing patches; irregular black tips","Underside":"Complex mosaic; 4–5 small hindwing eyespots","Flight Period":"Year-round; massive irruptions Mar–May","Host Plants":"Polyphagous — Malva, Cirsium, Ambrosia","Habitat":"Everywhere during irruptions"},"mo":[1,2,3,4,5,6,7,8,9,10,11,12],"pk":[3,4,5],"hp":"Asteraceae: thistles (Cirsium); also Urticaceae, Malvaceae","elev":"wide"},{"id":"va1","cn":"West Coast Lady","sn":"Vanessa annabella","fam":"Nymphalidae","st":"common","desc":"LA's resident Vanessa. Isolated orange costal forewing bar diagnostic.","fm":{"Wingspan":"2–2.5 in","Upperside":"Orange; isolated orange costal bar (diagnostic)","Underside":"Complex pattern; small eyespots","Flight Period":"Year-round","Host Plants":"Malvaceae, Urticaceae","Habitat":"Gardens, fields, chaparral edges"},"mo":[1,2,3,4,5,6,7,8,9,10,11,12],"pk":[3,4,5,9,10],"hp":"Malvaceae: mallows (Malva, Sphaeralcea); Urticaceae: nettle","elev":"foot,mid"},{"id":"vt1","cn":"Red Admiral","sn":"Vanessa atalanta","fam":"Nymphalidae","st":"common","desc":"Unmistakable black with vivid red-orange forewing band. Males aggressively territorial.","fm":{"Wingspan":"2–2.5 in","Upperside":"Black with red-orange forewing band; red hindwing border; white apical spots","Underside":"Cryptic dark mottling","Flight Period":"Year-round; peaks spring/fall","Host Plants":"Urtica (stinging nettle)","Habitat":"Riparian areas, shaded gardens"},"mo":[1,2,3,4,5,6,7,8,9,10,11,12],"pk":[],"hp":"Urticaceae: Urtica dioica (stinging nettle)","elev":"low,foot,mid"},{"id":"jc1","cn":"Common Buckeye","sn":"Junonia coenia","fam":"Nymphalidae","st":"common","desc":"Large eyespots the most prominent field mark of any LA butterfly.","fm":{"Wingspan":"1.5–2.5 in","Upperside":"Brown; 2 forewing + 2 hindwing eyespots; orange bars","Underside":"Seasonally variable — tan/rose to deep brown","Flight Period":"Year-round; peak spring–fall","Host Plants":"Plantago, Antirrhinum; Acanthaceae","Habitat":"Open disturbed ground, trails"},"mo":[1,2,3,4,5,6,7,8,9,10,11,12],"pk":[],"hp":"Plantago, Antirrhinum; Acanthaceae","elev":"low,foot"},{"id":"na1","cn":"Mourning Cloak","sn":"Nymphalis antiopa","fam":"Nymphalidae","st":"common","desc":"Among longest-lived butterflies (10–11 months). Overwinters as adult.","fm":{"Wingspan":"2.5–3.5 in","Upperside":"Deep maroon with cream border and blue spot row","Underside":"Dark bark-like camouflage","Flight Period":"Nearly year-round; adults overwinter","Host Plants":"Salix, Ulmus, Celtis, Populus","Habitat":"Riparian woodland, mountain canyons"},"mo":[1,2,3,4,5,6,7,8,9,10,11,12],"pk":[3,4,9,10],"hp":"Salicaceae: Salix (willows), Ulmus (elms), Populus (poplars)","elev":"wide"},{"id":"nc1","cn":"California Tortoiseshell","sn":"Nymphalis californica","fam":"Nymphalidae","st":"rare","desc":"Erupts in massive irruptions some years from Sierra Nevada. In non-irruption years, absent from LA County.","fm":{"Wingspan":"1.5–2.5 in","Upperside":"Bright orange with large black spots; dark borders","Underside":"Dark bark-like camouflage","Flight Period":"May–Sep; irruption-dependent in LA","Host Plants":"Ceanothus","Habitat":"Mountain chaparral; coastal during irruptions"},"mo":[5,6,7,8,9],"pk":[],"hp":"Rhamnaceae: Ceanothus spp.","elev":"foot,mid,high"},{"id":"ll1","cn":"Lorquin's Admiral","sn":"Limenitis lorquini","fam":"Nymphalidae","st":"common","desc":"Stunning riparian glider. Bold white band and orange forewing tips.","fm":{"Wingspan":"2–3 in","Upperside":"Black with white median band; orange forewing tips","Underside":"Orange-brown with white band; blue-gray margins","Flight Period":"Mar–Oct; 2–3 broods","Host Plants":"Salix, Populus, Prunus","Habitat":"Riparian corridors, urban willows"},"mo":[3,4,5,6,7,8,9,10],"pk":[],"hp":"Salicaceae: willows, poplars; Rosaceae: Prunus","elev":"low,foot,mid"},{"id":"ac1","cn":"California Sister","sn":"Adelpha californica","fam":"Nymphalidae","st":"common","desc":"LA's signature oak woodland butterfly. Graceful glide through live oak canopy.","fm":{"Wingspan":"2.5–3 in","Upperside":"Dark with bold white band; large orange apex patch","Underside":"Complex blue, orange, cream, brown bands","Flight Period":"Apr–Oct; 1–2 broods","Host Plants":"Quercus agrifolia (coast live oak)","Habitat":"Oak woodland, chaparral, foothill canyons"},"mo":[4,5,6,7,8,9,10],"pk":[],"hp":"Fagaceae: Quercus chrysolepis (canyon live oak)","elev":"foot,mid"},{"id":"my1","cn":"Mylitta Crescent","sn":"Phyciodes mylitta","fam":"Nymphalidae","st":"common","desc":"Small, intricately patterned crescent. Low flight through thistle patches.","fm":{"Wingspan":"1–1.5 in","Upperside":"Orange with complex black reticulation","Underside":"Cream with tan patch and fine markings","Flight Period":"Mar–Oct; 3+ broods","Host Plants":"Cirsium (thistles)","Habitat":"Open fields, streambanks with thistles"},"mo":[3,4,5,6,7,8,9,10],"pk":[],"hp":"Cirsium (thistles)","elev":"low,foot,mid"},{"id":"ca2","cn":"Common Wood-Nymph","sn":"Cercyonis pegala","fam":"Nymphalidae","st":"uncommon","desc":"Large brown satyr with prominent yellow-ringed eyespots. Slow bobbing flight.","fm":{"Wingspan":"2–2.5 in","Upperside":"Brown with 2 forewing eyespots in yellow patch","Underside":"Brown with eyespots and striping","Flight Period":"Jun–Sep; single brood","Host Plants":"Poaceae — Danthonia, Stipa, Elymus","Habitat":"Grasslands, oak woodland edges"},"mo":[6,7,8,9],"pk":[],"hp":"Poaceae — Danthonia, Stipa, Elymus","elev":"foot,mid"},{"id":"hp1","cn":"Fiery Skipper","sn":"Hylephila phyleus","fam":"Hesperiidae","st":"common","desc":"Most common lawn skipper in urban LA. Rapid darting flight low over turf.","fm":{"Wingspan":"1–1.5 in","Upperside":"Bright orange (♂) with jagged border; brown (♀)","Underside":"Orange with scattered dark spots (♂)","Flight Period":"Year-round; 3+ broods","Host Plants":"Bermuda, St. Augustine, crabgrass","Habitat":"Lawns, parks, playing fields"},"mo":[1,2,3,4,5,6,7,8,9,10,11,12],"pk":[],"hp":"Poaceae: Bermuda grass, crabgrass, lawn grasses","elev":"low"},{"id":"et1","cn":"Mournful Duskywing","sn":"Erynnis tristis","fam":"Hesperiidae","st":"common","desc":"Dark oak-associated skipper. White hindwing fringe diagnostic.","fm":{"Wingspan":"1–1.5 in","Upperside":"Dark brown-black; conspicuous white hindwing fringe","Underside":"Dark with bold white fringe","Flight Period":"Mar–Oct; 2–3 broods","Host Plants":"Quercus agrifolia","Habitat":"Oak woodland, chaparral"},"mo":[3,4,5,6,7,8,9,10],"pk":[],"hp":"Fagaceae: Quercus agrifolia (coast live oak), interior live oak","elev":"foot,mid"},{"id":"ef1","cn":"Funereal Duskywing","sn":"Erynnis funeralis","fam":"Hesperiidae","st":"common","desc":"Narrower white fringe than Mournful; legume host plants.","fm":{"Wingspan":"1–1.5 in","Upperside":"Dark; narrow white hindwing fringe","Underside":"Dark with thin white fringe","Flight Period":"Year-round; multiple broods","Host Plants":"Vicia, Medicago, Lotus","Habitat":"Open areas, gardens, agricultural edges"},"mo":[1,2,3,4,5,6,7,8,9,10,11,12],"pk":[],"hp":"Fabaceae: Acmispon glaber (deerweed), Olneya, other legumes","elev":"low"},{"id":"lm2","cn":"Umber Skipper","sn":"Lon melane","fam":"Hesperiidae","st":"common","desc":"Chunky dark skipper with warm umber tones.","fm":{"Wingspan":"1–1.5 in","Upperside":"Dark brown with amber-orange spots","Underside":"Red-brown with paler spots","Flight Period":"Year-round","Host Plants":"Various grasses","Habitat":"Shaded gardens, parks, riparian"},"mo":[1,2,3,4,5,6,7,8,9,10,11,12],"pk":[],"hp":"Various grasses","elev":"low,foot,mid"},{"id":"bc3","cn":"Common Checkered-Skipper","sn":"Burnsius communis","fam":"Hesperiidae","st":"common","desc":"Small, boldly checkered black-and-white. Males blue-gray fresh.","fm":{"Wingspan":"⅔ in–1 in","Upperside":"Black with white checkering; ♂ blue-gray hairs","Underside":"White with olive-tan bands","Flight Period":"Year-round; multiple broods","Host Plants":"Malva, Sida, Sidalcea","Habitat":"Disturbed areas, roadsides, gardens"},"mo":[1,2,3,4,5,6,7,8,9,10,11,12],"pk":[],"hp":"Malva, Sida, Sidalcea","elev":"low"},{"id":"ps4","cn":"Sandhill Skipper","sn":"Polites sabuleti","fam":"Hesperiidae","st":"common","desc":"Small tawny skipper. Prominent veined underside in LA populations.","fm":{"Wingspan":"⅔ in–1 in","Upperside":"Tawny (♂) with dark borders","Underside":"Yellow-green to olive with pale veining","Flight Period":"Mar–Oct; 2–3 broods","Host Plants":"Bermuda, saltgrass","Habitat":"Lawns, salt marshes, grasslands"},"mo":[3,4,5,6,7,8,9,10],"pk":[],"hp":"Poaceae: Bermuda grass, blue grass","elev":"coast"},{"id":"ep1","cn":"Eufala Skipper","sn":"Lerodea eufala","fam":"Hesperiidae","st":"common","desc":"Plain gray-brown, often overlooked. Very common in irrigated landscapes.","fm":{"Wingspan":"¾ in–1 in","Upperside":"Gray-brown; faint pale forewing spots","Underside":"Gray-brown with small pale hindwing spots","Flight Period":"Year-round; multiple broods","Host Plants":"Bermuda, crabgrass, Johnson grass","Habitat":"Urban lawns, agricultural fields"},"mo":[1,2,3,4,5,6,7,8,9,10,11,12],"pk":[],"hp":"Poaceae: various grasses inc. Bermuda, Johnson grass","elev":"low"},{"id":"ew1","cn":"Northern White-Skipper","sn":"Heliopetes ericetorum","fam":"Hesperiidae","st":"uncommon","desc":"Bright white skipper of arid hillsides.","fm":{"Wingspan":"1–1.5 in","Upperside":"White with narrow dark borders","Underside":"White with olive-tan veining","Flight Period":"Apr–Sep; 2 broods","Host Plants":"Sphaeralcea, Malva","Habitat":"Arid hillsides, desert washes"},"mo":[4,5,6,7,8,9],"pk":[],"hp":"Sphaeralcea, Malva","elev":"low,foot"},{"id":"am1","cn":"Mormon Metalmark","sn":"Apodemia mormo","fam":"Riodinidae","st":"uncommon","desc":"LA's only metalmark. Intricate checkered pattern with metallic silver. Tied to Eriogonum.","fm":{"Wingspan":"¾ in–1 in","Upperside":"Dark brown checkered with orange/white; metallic silver scales","Underside":"Orange with black-white checkering and silver spots","Flight Period":"Aug–Oct; single late brood (unusual timing)","Host Plants":"Eriogonum fasciculatum","Habitat":"Coastal sage scrub, buckwheat hillsides"},"mo":[8,9,10],"pk":[],"hp":"Eriogonum fasciculatum","elev":"coast"},{"id":"cn1","cn":"Nelson's Hairstreak","sn":"Callophrys nelsoni","fam":"Lycaenidae","st":"rare","desc":"Dark reddish-brown hairstreak of coniferous forests. San Gabriel Mtns above 5,000'.","fm":{"Wingspan":"¾ in–1 in","Upperside":"Dark reddish-brown","Underside":"Reddish-brown; irregular white postmedian line","Flight Period":"Apr–Jun; single brood","Host Plants":"Cupressaceae — incense-cedar, junipers","Habitat":"Mixed conifer forest above 5,000'"},"mo":[4,5,6],"pk":[],"hp":"Cupressaceae — incense-cedar, junipers","elev":"mid,high"},{"id":"ml1","cn":"Leda Ministreak","sn":"Ministrymon leda","fam":"Lycaenidae","st":"uncommon","desc":"Tiny blue-gray hairstreak with red-orange hindwing patches. Mesquite associate.","fm":{"Wingspan":"⅔ in","Upperside":"Blue-gray with orange marginal spots","Underside":"Gray with red-orange patches; white postmedian line","Flight Period":"Apr–Oct; multiple broods","Host Plants":"Prosopis (mesquite)","Habitat":"Desert washes, warm valleys"},"mo":[4,5,6,7,8,9,10],"pk":[],"hp":"Prosopis (mesquite)","elev":"low,foot"},{"id":"ib1","cn":"Boisduval's Blue","sn":"Icaricia icarioides","fam":"Lycaenidae","st":"rare","desc":"Declining lupine-specialist blue. Now restricted to montane sites.","fm":{"Wingspan":"¾ in–1 in","Upperside":"Violet-blue (♂); dark brown with blue basal (♀)","Underside":"Gray with black spots in white halos; no orange band","Flight Period":"Apr–Jul; single brood","Host Plants":"Lupinus (native lupines only)","Habitat":"Mountain meadows, conifer openings"},"mo":[4,5,6,7],"pk":[],"hp":"Lupinus (native lupines only)","elev":"foot,mid"},{"id":"ss1","cn":"Sylvan Hairstreak","sn":"Satyrium sylvinus","fam":"Lycaenidae","st":"uncommon","desc":"Grayish hairstreak of riparian willows.","fm":{"Wingspan":"¾ in–1 in","Upperside":"Plain gray-brown","Underside":"Pale gray with faint postmedian dashes","Flight Period":"Jun–Aug; single brood","Host Plants":"Salix (willows)","Habitat":"Riparian woodland"},"mo":[6,7,8],"pk":[],"hp":"Salix (willows)","elev":"foot,mid"},{"id":"vv1","cn":"American Lady","sn":"Vanessa virginiensis","fam":"Nymphalidae","st":"uncommon","desc":"Two large (not 4–5 small) hindwing underside eyespots diagnostic. Cobwebby underwing.","fm":{"Wingspan":"2–2.5 in","Upperside":"Orange; small white spot in forewing cell","Underside":"Cobwebby pink-brown; 2 large hindwing eyespots","Flight Period":"Year-round; less common than V. cardui","Host Plants":"Gnaphalium, Antennaria, Artemisia","Habitat":"Open sunny areas, meadows"},"mo":[1,2,3,4,5,6,7,8,9,10,11,12],"pk":[],"hp":"Asteraceae: Pseudognaphalium, Gnaphalium (cudweeds)","elev":"low,foot"},{"id":"ps3","cn":"Great Basin Wood-Nymph","sn":"Cercyonis sthenele","fam":"Nymphalidae","st":"uncommon","desc":"Smaller and paler than Common Wood-Nymph. Dry grassy hillsides.","fm":{"Wingspan":"1.5–2 in","Upperside":"Gray-brown; 1–2 small eyespots; minimal yellow","Underside":"Gray-brown with striations","Flight Period":"Jun–Aug; single brood","Host Plants":"Native bunchgrasses","Habitat":"Dry grasslands, chaparral openings"},"mo":[6,7,8],"pk":[],"hp":"Native bunchgrasses","elev":"foot,mid"},{"id":"sg1","cn":"Strecker's Giant-Skipper","sn":"Megathymus streckeri","fam":"Hesperiidae","st":"historical","desc":"Historical record only — formerly bred on yucca in Antelope Valley. Not documented in LA County since early 20th century. Extirpated from most of SoCal range.","fm":{"Wingspan":"1.5–2.5 in","Upperside":"Dark brown-black with yellow forewing spots","Underside":"Dark with frosted gray overscaling; yellow spots","Flight Period":"Historically Apr–May; single brood","Host Plants":"Yucca spp.","Habitat":"High desert yucca grasslands (historical)"},"mo":[4,5],"pk":[],"hp":"Yucca spp.","elev":"low,foot"},{"id":"qc1","cn":"Quino Checkerspot","sn":"Euphydryas editha quino","fam":"Nymphalidae","st":"endangered","desc":"Federally Endangered. Historically southern LA County; now restricted to Riverside/San Diego. Extirpated from LA County.","fm":{"Wingspan":"1.5 in","Upperside":"Orange, cream, and black checkerspot pattern","Underside":"Cream with red-orange and black bands","Flight Period":"Feb–Apr; single brood; highly weather-dependent","Host Plants":"Plantago erecta (dwarf plantain)","Habitat":"Coastal sage scrub, grasslands (extirpated from LA)"},"ssp":true,"mo":[2,3,4],"pk":[],"hp":"Plantago erecta (dwarf plantain)","elev":"low,foot"},{"id":"hc1","cn":"Common Branded Skipper","sn":"Hesperia comma","fam":"Hesperiidae","st":"uncommon","desc":"Upland skipper with prominent silver-white chevron on underside.","fm":{"Wingspan":"¾ in–1 in","Upperside":"Orange (♂) with dark stigma; brown (♀)","Underside":"Olive/golden with silver-white chevron spots","Flight Period":"Jul–Sep; single brood","Host Plants":"Native bunchgrasses","Habitat":"Mountain meadows, grasslands above 4,000'"},"mo":[7,8,9],"pk":[],"hp":"Native bunchgrasses","elev":"foot,mid"},{"id":"wb1","cn":"White-lined Skipper","sn":"Hesperia lindseyi","fam":"Hesperiidae","st":"uncommon","desc":"A coastal chaparral skipper similar to branded skipper but flying earlier in season.","fm":{"Wingspan":"1 in","Upperside":"Tawny orange (♂); brown (♀)","Underside":"Olive-green with pale elongated spots","Flight Period":"Apr–Jun; single brood","Host Plants":"Poaceae — native bunchgrasses","Habitat":"Chaparral, coastal sage scrub openings"},"mo":[4,5,6],"pk":[],"hp":"Poaceae — native bunchgrasses","elev":"foot,mid"},{"id":"pd3","cn":"Desert Black Swallowtail","sn":"Papilio polyxenes coloro","fam":"Papilionidae","st":"rare","desc":"Desert subspecies. Rare stray to NE LA County.","fm":{"Wingspan":"2.5–3 in","Upperside":"Black with yellow spot-band","Underside":"Yellow spots; orange eyespot","Flight":"Apr–Sep","Hosts":"Apiaceae","Habitat":"Desert washes; vagrant to LA basin"},"ssp":true,"mo":[3,4,5,6,7,8,9,10],"pk":[4,5,6],"elev":"low,foot"},{"id":"el2","cn":"Large Marble","sn":"Euchloe ausonides","fam":"Pieridae","st":"rare","desc":"Larger marble with bold green marbling. San Gabriel peaks only.","fm":{"Wingspan":"1.5–2 in","Upperside":"White; bold black discal bar","Underside":"Bold green marbling","Flight":"Apr–Jun; single brood","Hosts":"Brassicaceae","Habitat":"Mountain meadows above 5,000'"},"mo":[3,4,5,6,7,8,9,10],"pk":[4,5,6],"hp":"Brassicaceae: mustards, Arabis","elev":"mid,high"},{"id":"er1","cn":"Eastern Tailed-Blue","sn":"Cupido comyntas","fam":"Lycaenidae","st":"uncommon","desc":"Tiny blue with thin hindwing tails.","fm":{"Wingspan":"⅔ in–1 in","Upperside":"Blue (♂); gray-brown (♀)","Underside":"Pale gray; dark spots; orange marginal; thin tails","Flight":"Mar–Oct; multiple broods","Hosts":"Fabaceae — clovers, vetches","Habitat":"Moist meadows, riparian, gardens"},"mo":[3,4,5,6,7,8,9,10],"pk":[4,5,6],"elev":"low,foot"},{"id":"cr1","cn":"Ceraunus Blue","sn":"Hemiargus ceraunus","fam":"Lycaenidae","st":"uncommon","desc":"Neotropical blue. Single prominent hindwing eyespot below.","fm":{"Wingspan":"⅔ in–1 in","Upperside":"Blue (♂); brown (♀)","Underside":"Gray; single large hindwing eyespot","Flight":"Year-round in warm areas","Hosts":"Acacia, Prosopis, Dalea","Habitat":"Desert washes, warm urban edges"},"mo":[3,4,5,6,7,8,9,10],"pk":[4,5,6],"elev":"low,foot"},{"id":"rv1","cn":"Reakirt's Blue","sn":"Echinargus isola","fam":"Lycaenidae","st":"uncommon","desc":"Prominent round spots in white halos on underside. Mesquite.","fm":{"Wingspan":"⅔ in–1 in","Upperside":"Blue (♂); brown (♀)","Underside":"Row of round black spots in white halos","Flight":"Mar–Nov","Hosts":"Prosopis, Medicago, Dalea","Habitat":"Desert washes, agricultural edges"},"mo":[3,4,5,6,7,8,9,10],"pk":[4,5,6],"elev":"low,foot"},{"id":"sn1","cn":"Satyr Comma","sn":"Polygonia satyrus","fam":"Nymphalidae","st":"uncommon","desc":"Most common LA anglewing. Golden with ragged edges, silver comma below.","fm":{"Wingspan":"2 in","Upperside":"Golden-orange; dark spots; ragged edges","Underside":"Brown bark-like; silver comma","Flight":"Mar–Oct; 2 broods; overwinters","Hosts":"Urtica (stinging nettle)","Habitat":"Riparian woodland, mountain canyons"},"mo":[3,4,5,6,7,8,9,10],"pk":[4,5,6],"hp":"Urticaceae: Urtica dioica (stinging nettle)","elev":"foot,mid"},{"id":"hn1","cn":"Hoary Comma","sn":"Polygonia gracilis","fam":"Nymphalidae","st":"rare","desc":"Mountain anglewing. San Gabriel Mtns above 6,000'.","fm":{"Wingspan":"2 in","Upperside":"Orange-brown; dark spots; ragged edges","Underside":"Dark; silver comma mark","Flight":"Jun–Sep; overwinters as adult","Hosts":"Ribes, Urtica","Habitat":"Mountain forest above 6,000'"},"mo":[3,4,5,6,7,8,9,10],"pk":[4,5,6],"elev":"foot,mid"},{"id":"tc1","cn":"Texan Crescent","sn":"Anthanassa texana","fam":"Nymphalidae","st":"rare","desc":"Neotropical crescent. Irregular vagrant. Dark with white band.","fm":{"Wingspan":"1–1.5 in","Upperside":"Dark with white median band; red basal","Underside":"Brown with pale banding","Flight":"Mar–Nov; sporadic","Hosts":"Acanthaceae","Habitat":"Desert washes; vagrant"},"mo":[3,4,5,6,7,8,9,10],"pk":[4,5,6],"elev":"low,foot"},{"id":"wl1","cn":"Woodland Skipper","sn":"Ochlodes sylvanoides","fam":"Hesperiidae","st":"common","desc":"Common fall skipper. Last skipper flying in autumn.","fm":{"Wingspan":"¾ in–1 in","Upperside":"Tawny-orange; dark borders","Underside":"Yellow-orange with pale spot-band","Flight":"Jul–Oct; single late brood","Hosts":"Poaceae","Habitat":"Grasslands, gardens in fall"},"mo":[3,4,5,6,7,8,9,10],"pk":[4,5,6],"hp":"Poaceae: native and non-native grasses","elev":"low"},{"id":"jg1","cn":"Julia's Skipper","sn":"Nastra julia","fam":"Hesperiidae","st":"uncommon","desc":"Tiny plain brown. Common in irrigated turf.","fm":{"Wingspan":"⅔ in–1 in","Upperside":"Plain brown; faint pale spots","Underside":"Tan-brown; unmarked","Flight":"Year-round","Hosts":"Lawn grasses","Habitat":"Irrigated lawns, parks"},"mo":[3,4,5,6,7,8,9,10],"pk":[4,5,6],"elev":"wide"},{"id":"cd2","cn":"Columbian Skipper","sn":"Hesperia columbia","fam":"Hesperiidae","st":"uncommon","desc":"Foothill grassland skipper. Angular silver spots below.","fm":{"Wingspan":"1–1.5 in","Upperside":"Tawny-orange; dark stigma","Underside":"Olive-green with silver spots","Flight":"Apr–Jun; single brood","Hosts":"Stipa, Festuca","Habitat":"Foothill grasslands"},"mo":[3,4,5,6,7,8,9,10],"pk":[4,5,6],"elev":"foot,mid"},{"id":"pg1","cn":"Propertius Duskywing","sn":"Erynnis propertius","fam":"Hesperiidae","st":"uncommon","desc":"Oak duskywing. Gray, no white hindwing fringe.","fm":{"Wingspan":"1–1.5 in","Upperside":"Dark gray-brown; pale forewing spots; gray fringe","Underside":"Dark","Flight":"Mar–Jun; single brood","Hosts":"Quercus spp.","Habitat":"Oak woodland"},"mo":[3,4,5,6,7,8,9,10],"pk":[4,5,6],"elev":"foot,mid"},{"id":"ff1","cn":"Pacuvius Duskywing","sn":"Erynnis pacuvius","fam":"Hesperiidae","st":"uncommon","desc":"Ceanothus-feeding duskywing.","fm":{"Wingspan":"1–1.5 in","Upperside":"Gray-brown; pale spots; no white fringe","Underside":"Dark with pale spots","Flight":"Apr–Jul","Hosts":"Ceanothus","Habitat":"Chaparral"},"mo":[3,4,5,6,7,8,9,10],"pk":[4,5,6],"elev":"foot,mid"},{"id":"ds1","cn":"Desert Checkered-Skipper","sn":"Burnsius philetas","fam":"Hesperiidae","st":"uncommon","desc":"Desert counterpart. Paler with more white.","fm":{"Wingspan":"¾ in–1 in","Upperside":"Pale gray-white; sparse checkering","Underside":"Nearly white; olive bands","Flight":"Year-round; peaks spring/fall","Hosts":"Sphaeralcea, Malva","Habitat":"Desert washes, arid scrub"},"mo":[3,4,5,6,7,8,9,10],"pk":[4,5,6],"elev":"low,foot"},{"id":"ra1","cn":"Rural Skipper","sn":"Ochlodes agricola","fam":"Hesperiidae","st":"uncommon","desc":"Woodland clearing skipper.","fm":{"Wingspan":"1 in","Upperside":"Orange-brown","Underside":"Orange-tan with pale spot-band","Flight":"May–Jul","Hosts":"Native grasses","Habitat":"Woodland clearings"},"mo":[3,4,5,6,7,8,9,10],"pk":[4,5,6],"elev":"foot,mid"},{"id":"br1","cn":"Brown Elfin","sn":"Callophrys augustinus","fam":"Lycaenidae","st":"uncommon","desc":"Small dark brown hairstreak of chaparral. Single spring brood. Perches with wings closed showing uniform brown underside.","fm":{"Wingspan":"¾ in–1 in","Upperside":"Dark brown (rarely seen)","Underside":"Uniform warm brown; darker basal area","Flight":"Mar–May; single brood","Hosts":"Ceanothus, Arctostaphylos, Dodecatheon","Habitat":"Chaparral, foothill scrub"},"mo":[3,4,5,6,7,8,9,10],"pk":[4,5,6],"elev":"foot,mid"},{"id":"sm2","cn":"Gold-hunter's Hairstreak","sn":"Satyrium auretorum","fam":"Lycaenidae","st":"uncommon","desc":"A warm brown oak-feeding hairstreak. Named for Gold Rush era collectors. Orange submarginal spots below.","fm":{"Wingspan":"1 in","Upperside":"Brown with faint orange spots","Underside":"Gray-brown; orange submarginal crescents; dark postmedian spots","Flight":"May–Jul; single brood","Hosts":"Quercus spp.","Habitat":"Oak woodland"},"mo":[3,4,5,6,7,8,9,10],"pk":[4,5,6],"elev":"foot,mid"},{"id":"mt1","cn":"Mountain Mahogany Hairstreak","sn":"Satyrium tetra","fam":"Lycaenidae","st":"uncommon","desc":"Gray hairstreak associated with mountain mahogany. Thin tails. Montane chaparral.","fm":{"Wingspan":"¾ in–1 in","Upperside":"Gray-brown","Underside":"Pale gray with dark postmedian line; small orange cap near tail","Flight":"Jun–Jul; single brood","Hosts":"Cercocarpus (mountain mahogany)","Habitat":"Montane chaparral above 4,000'"},"mo":[3,4,5,6,7,8,9,10],"pk":[4,5,6],"elev":"foot,mid"},{"id":"tl2","cn":"Thicket Hairstreak","sn":"Callophrys spinetorum","fam":"Lycaenidae","st":"uncommon","desc":"A reddish-brown hairstreak of mistletoe in conifers. Similar to Nelson's but warmer brown.","fm":{"Wingspan":"¾ in–1 in","Upperside":"Brown","Underside":"Reddish-brown with white postmedian line bordered blue","Flight":"May–Jul; single brood","Hosts":"Phoradendron (dwarf mistletoe) on conifers","Habitat":"Mixed conifer forest"},"mo":[3,4,5,6,7,8,9,10],"pk":[4,5,6],"elev":"mid,high"},{"id":"jh1","cn":"Juniper Hairstreak","sn":"Callophrys gryneus","fam":"Lycaenidae","st":"uncommon","desc":"Bright green underside (like Bramble) but on junipers. Desert edge and montane.","fm":{"Wingspan":"¾ in–1 in","Upperside":"Brown","Underside":"Bright green with white postmedian line","Flight":"Apr–Jun; single brood","Hosts":"Juniperus (junipers), Cupressus","Habitat":"Juniper woodland, desert edge with junipers"},"mo":[3,4,5,6,7,8,9,10],"pk":[4,5,6],"elev":"foot,mid"},{"id":"ws4","cn":"Western Green Hairstreak","sn":"Callophrys affinis","fam":"Lycaenidae","st":"uncommon","desc":"Buckwheat-feeding green hairstreak. Smaller and duller than Bramble. Spring flier.","fm":{"Wingspan":"⅔ in–1 in","Upperside":"Brown","Underside":"Gray-green; white postmedian line sometimes reduced","Flight":"Mar–May; single brood","Hosts":"Eriogonum spp.","Habitat":"Coastal sage scrub, chaparral with buckwheat"},"mo":[3,4,5,6,7,8,9,10],"pk":[4,5,6],"elev":"foot,mid"},{"id":"sp5","cn":"Sonoran Blue","sn":"Philotes sonorensis","fam":"Lycaenidae","st":"rare","desc":"Tiny blue tightly associated with Dudleya (liveforever succulents). One of earliest spring butterflies. Rocky coastal bluffs.","fm":{"Wingspan":"⅔ in–¾ in","Upperside":"Blue (♂); brown with blue base (♀); orange HW spots","Underside":"White with black spots; orange HW band","Flight":"Jan–Apr; single very early brood","Hosts":"Dudleya (liveforever) — obligate","Habitat":"Rocky coastal bluffs, cliff faces with Dudleya"},"mo":[3,4,5,6,7,8,9,10],"pk":[4,5,6],"elev":"coast"},{"id":"ar1","cn":"Arrowhead Blue","sn":"Glaucopsyche piasus","fam":"Lycaenidae","st":"uncommon","desc":"White arrowhead-shaped spots on hindwing underside diagnostic. Lupine specialist.","fm":{"Wingspan":"1 in","Upperside":"Blue-violet (♂); brown with blue base (♀)","Underside":"Gray with white arrowhead-shaped HW spots","Flight":"Apr–Jun; single brood","Hosts":"Lupinus spp.","Habitat":"Coastal sage, chaparral with lupines"},"mo":[3,4,5,6,7,8,9,10],"pk":[4,5,6],"elev":"foot,mid"},{"id":"sb3","cn":"Western Tailed-Blue","sn":"Cupido amyntula","fam":"Lycaenidae","st":"uncommon","desc":"Tiny pale blue of mesic habitats. Very small — among tiniest LA blues after Pygmy.","fm":{"Wingspan":"⅔ in–1 in","Upperside":"Pale blue (♂); gray (♀)","Underside":"Pale gray-white with scattered dark dots","Flight":"Apr–Jul; 1–2 broods","Hosts":"Astragalus, Lathyrus, Lotus","Habitat":"Mountain meadows, riparian edges"},"mo":[3,4,5,6,7,8,9,10],"pk":[4,5,6],"elev":"foot,mid"},{"id":"mc2","cn":"Northern Checkerspot","sn":"Chlosyne palla","fam":"Nymphalidae","st":"uncommon","desc":"Orange-and-black checkerspot of mountain meadows. Distinguished from Mylitta by habitat and larger size.","fm":{"Wingspan":"1.5 in","Upperside":"Orange with complex black pattern and cream spots","Underside":"Cream and orange with dark-outlined cells","Flight":"May–Jul; single brood","Hosts":"Aster, Castilleja","Habitat":"Mountain meadows, open woodland above 4,000'"},"mo":[3,4,5,6,7,8,9,10],"pk":[4,5,6],"elev":"foot,mid"},{"id":"lc1","cn":"Leanira Checkerspot","sn":"Chlosyne leanira","fam":"Nymphalidae","st":"uncommon","desc":"Black with cream bands and orange patches. Multiple SoCal subspecies.","fm":{"Wingspan":"1–1.5 in","Upperside":"Black with cream/white bands; orange patches","Underside":"Cream with orange and black pattern","Flight":"Apr–Jun; single brood","Hosts":"Castilleja (Indian paintbrush)","Habitat":"Desert scrub, chaparral, rocky slopes"},"mo":[3,4,5,6,7,8,9,10],"pk":[4,5,6],"elev":"foot,mid"},{"id":"ns2","cn":"Great Basin Fritillary","sn":"Argynnis egleis","fam":"Nymphalidae","st":"rare","desc":"A montane fritillary at range edge in the San Gabriel Mtns. Greenish underside.","fm":{"Wingspan":"2 in","Upperside":"Tawny; dark spots","Underside":"Greenish with burnished silver spots","Flight":"Jun–Aug; single brood","Hosts":"Viola spp.","Habitat":"Mountain meadows above 6,000' (rare in LA)"},"mo":[3,4,5,6,7,8,9,10],"pk":[4,5,6],"elev":"mid,high"},{"id":"wb5","cn":"Red-spotted Purple","sn":"Limenitis arthemis arizonensis","fam":"Nymphalidae","st":"rare","desc":"A Batesian mimic of Pipevine Swallowtail. Blue-black with orange spots. Rare vagrant to desert edge LA.","fm":{"Wingspan":"2.5–3 in","Upperside":"Blue-black iridescence; no white band","Underside":"Dark with orange submarginal spots; blue marginal area","Flight":"May–Sep","Hosts":"Prunus, Salix, Populus","Habitat":"Riparian; rare vagrant to LA desert edge"},"ssp":true,"mo":[3,4,5,6,7,8,9,10],"pk":[4,5,6],"elev":"low,foot"},{"id":"cm3","cn":"Common Mestra","sn":"Mestra amymone","fam":"Nymphalidae","st":"vagrant","desc":"Subtropical vagrant. White/gray with orange FW patch. Reaches LA County very rarely from Mexico.","fm":{"Wingspan":"1.5–2 in","Upperside":"White-gray with orange forewing costal patch","Underside":"White with faint banding","Flight":"Year-round in tropics; vagrant to LA","Hosts":"Tragia (noseburn)","Habitat":"Desert edges during vagrant events"},"mo":[3,4,5,6,7,8,9,10],"pk":[4,5,6],"elev":"low,foot"},{"id":"as5","cn":"Arizona Skipper","sn":"Codatractus arizonensis","fam":"Hesperiidae","st":"rare","desc":"Large dark skipper. Desert canyons with Robinia (locust). Rare vagrant to LA from AZ.","fm":{"Wingspan":"1.5–2 in","Upperside":"Dark brown with faint pale spots","Underside":"Dark with violet sheen","Flight":"Apr–Aug","Hosts":"Robinia neomexicana","Habitat":"Desert canyons; rare vagrant"},"mo":[3,4,5,6,7,8,9,10],"pk":[4,5,6],"elev":"foot,mid"},{"id":"mv3","cn":"Mojave Sootywing","sn":"Hesperopsis libya","fam":"Hesperiidae","st":"uncommon","desc":"Small dark checkered skipper of desert saltbush flats. Atriplex specialist.","fm":{"Wingspan":"⅔ in–1 in","Upperside":"Black-brown with small white checkers","Underside":"Dark with scattered white spots","Flight":"Mar–Oct; 2–3 broods","Hosts":"Atriplex (saltbush)","Habitat":"Desert saltbush flats, alkali areas"},"mo":[3,4,5,6,7,8,9,10],"pk":[4,5,6],"elev":"low"},{"id":"cf2","cn":"Common Sootywing","sn":"Pholisora catullus","fam":"Hesperiidae","st":"uncommon","desc":"Dark skipper with white head spots. Associated with Amaranthaceae.","fm":{"Wingspan":"⅔ in–1 in","Upperside":"Black-brown with fine white flecking; white head spots","Underside":"Black-brown with faint pale spots","Flight":"Mar–Oct; 2–3 broods","Hosts":"Amaranthaceae — Chenopodium, Amaranthus","Habitat":"Disturbed ground, agricultural edges, gardens"},"mo":[3,4,5,6,7,8,9,10],"pk":[4,5,6],"elev":"low"},{"id":"fs2","cn":"Sachem","sn":"Atalopedes campestris","fam":"Hesperiidae","st":"common","desc":"Large orange skipper. ♂ with large brown patch on hindwing underside.","fm":{"Wingspan":"1–1.5 in","Upperside":"♂: bright orange with dark borders. ♀: dark with orange spots.","Underside":"♂: orange-tan with large diffuse brown HW patch (diagnostic)","Flight":"Year-round; multiple broods","Hosts":"Bermuda, lawn grasses","Habitat":"Lawns, parks, irrigated turf"},"mo":[3,4,5,6,7,8,9,10],"pk":[4,5,6],"hp":"Poaceae: Bermuda grass, crabgrass, Dallis grass","elev":"low,foot"},{"id":"ls4","cn":"Leussler's Branded Skipper","sn":"Hesperia colorado leussleri","fam":"Hesperiidae","st":"rare","desc":"Subspecies of Western Branded Skipper. Late-summer flier in SoCal mountains; grasses. Distinguished from other Hesperia by ventral hindwing pattern.","fm":{"Wingspan":"1–1.5 in","Upperside":"Orange-brown; dark margins","Underside":"Rust-orange with cream chevron spots","Flight":"Aug–Sep; single late brood","Hosts":"Native bunchgrasses (Stipa, Elymus)","Habitat":"Mountain meadows above 5,000'"},"ssp":true,"mo":[3,4,5,6,7,8,9,10],"pk":[4,5,6],"elev":"mid,high"},{"id":"sb5","cn":"Silver-spotted Skipper","sn":"Epargyreus clarus","fam":"Hesperiidae","st":"uncommon","desc":"Large skipper with prominent silver-white HW patch below. Strong rapid flight. Widespread but irregular in LA.","fm":{"Wingspan":"1.5–2 in","Upperside":"Dark brown with gold FW spots; elongated HW","Underside":"Dark with large silver-white HW patch (diagnostic)","Flight":"Apr–Sep; 1–2 broods","Hosts":"Fabaceae — Robinia, Wisteria, Lathyrus","Habitat":"Woodland edges, gardens with legume vines"},"mo":[3,4,5,6,7,8,9,10],"pk":[4,5,6],"elev":"low"},{"id":"lg2","cn":"Long-tailed Skipper","sn":"Urbanus proteus","fam":"Hesperiidae","st":"vagrant","desc":"Neotropical skipper with iridescent green thorax and long HW tails. Rare vagrant to SoCal.","fm":{"Wingspan":"1.5–2 in","Upperside":"Dark with iridescent blue-green thorax; long HW tails","Underside":"Brown with dark bands; long tails","Flight":"Year-round in tropics; vagrant to LA summer–fall","Hosts":"Fabaceae — beans, Desmodium","Habitat":"Urban gardens during vagrant events"},"mo":[3,4,5,6,7,8,9,10],"pk":[4,5,6],"elev":"low"},{"id":"dn1","cn":"Dotted Blue","sn":"Euphilotes enoptes","fam":"Lycaenidae","st":"uncommon","desc":"Buckwheat specialist similar to Square-spotted. Dots not squares. Multiple local subspecies.","fm":{"Wingspan":"⅔ in–1 in","Upperside":"Blue (♂); brown (♀)","Underside":"Gray; orange HW band with round (not square) spots","Flight":"Apr–Jul; single brood sync with Eriogonum","Hosts":"Eriogonum spp. — flowers","Habitat":"Coastal sage, chaparral slopes with buckwheat"},"mo":[3,4,5,6,7,8,9,10],"pk":[4,5,6],"elev":"foot,mid"},{"id":"we1","cn":"Western Elfin","sn":"Callophrys iroides","fam":"Lycaenidae","st":"uncommon","desc":"Reddish-brown elfin of chaparral. Jagged underside postmedian line distinctive.","fm":{"Wingspan":"¾ in–1 in","Upperside":"Dark brown","Underside":"Rich reddish-brown with irregular/jagged pale postmedian line","Flight":"Feb–May; single brood","Hosts":"Ceanothus, Cercocarpus","Habitat":"Chaparral, foothill scrub"},"mo":[3,4,5,6,7,8,9,10],"pk":[4,5,6],"elev":"foot,mid"},{"id":"mb2","cn":"Melissa Blue","sn":"Icaricia melissa","fam":"Lycaenidae","st":"uncommon","desc":"A blue of mountain meadows. Similar to Acmon but typically at higher elevation. Orange HW band usually narrower.","fm":{"Wingspan":"¾ in–1 in","Upperside":"Blue (♂); brown with orange band (♀)","Underside":"Gray; orange HW band typically narrower than Acmon","Flight":"May–Sep; 2 broods at lower elevations","Hosts":"Astragalus, Lupinus, Medicago","Habitat":"Mountain meadows, grasslands, alfalfa fields"},"mo":[3,4,5,6,7,8,9,10],"pk":[4,5,6],"elev":"foot,mid,high"},{"id":"gr1","cn":"Western Giant Swallowtail","sn":"Heraclides rumiko","fam":"Papilionidae","st":"common","desc":"Recently split from P. cresphontes. The western population is now its own species. North America's largest butterfly — wingspan to 6 in. Expanding rapidly in SoCal via ornamental citrus. 3,000+ iNat obsin LA County.","fm":{"Wingspan":"4–6 in (largest LA butterfly)","Upperside":"Black-brown with diagonal yellow spot-band; yellow tail spots","Underside":"Predominantly creamy-yellow with blue and red hindwing patches","Flight Period":"Apr–Nov; 2+ broods","Host Plants":"Rutaceae — Citrus, Zanthoxylum, Ptelea, Ruta","Habitat":"Urban areas with citrus; riparian; gardens"},"mo":[4,5,6,7,8,9,10,11],"pk":[],"hp":"Rutaceae — Citrus, Zanthoxylum, Ptelea, Ruta","elev":"low,foot,mid"},{"id":"ec6","cn":"Variable Checkerspot","sn":"Euphydryas chalcedona","fam":"Nymphalidae","st":"common","desc":"A large, showy checkerspot common in chaparral and coastal sage scrub. Highly variable — populations range from predominantly black to heavily orange/red. Larvae feed communally in silk webs on host plants. 1,863 LA County iNat obs","fm":{"Wingspan":"1.5–2 in","Upperside":"Black with red/orange/cream checkered spots; highly variable between populations","Underside":"Cream/yellow with red and black bands and spots","Flight Period":"Mar–Jun; single brood","Host Plants":"Scrophulariaceae — Diplacus (monkeyflower), Castilleja, Penstemon; also Plantago","Habitat":"Chaparral, coastal sage scrub, oak woodland edges"},"mo":[3,4,5,6],"pk":[],"hp":"Scrophulariaceae — Diplacus (monkeyflower), Castilleja, Penstemon; also Plantago","elev":"foot,mid"},{"id":"jg2","cn":"Gray Buckeye","sn":"Junonia grisea","fam":"Nymphalidae","st":"common","desc":"Recently split from Common Buckeye (J. coenia). The western/dry-habitat species — grayer overall, eyespots tend smaller. The dominant buckeye in arid LA County habitats.","fm":{"Wingspan":"1.5–2 in","Upperside":"Gray-brown (less warm than J. coenia) with eyespots; eyespots may average smaller","Underside":"Variable — tan to rose-brown; often grayer than coenia","Flight Period":"Year-round; multiple broods","Host Plants":"Plantago, Antirrhinum, Mimulus; Acanthaceae","Habitat":"Drier, more arid habitats than J. coenia — desert edges, dry washes, chaparral trails"},"mo":[1,2,3,4,5,6,7,8,9,10,11,12],"pk":[],"hp":"Plantaginaceae: Plantago; Orobanchaceae: Mimulus, snapdragons","elev":"foot,mid"},{"id":"ia1","cn":"Acmon Blue","sn":"Icaricia acmon","fam":"Lycaenidae","st":"common","desc":"Most common small blue in LA chaparral. Orange HW marginal band with metallic green caps diagnostic. Genus recently moved from Plebejus to Icaricia on iNat. 1,482 LA County obs","fm":{"Wingspan":"⅔ in–1 in","Upperside":"Blue (♂) or brown with orange marginal band (♀)","Underside":"Gray with black spots; vivid orange HW band with metallic green caps","Flight Period":"Mar–Oct; 2–3 broods","Host Plants":"Eriogonum, Lotus, Astragalus","Habitat":"Chaparral, coastal sage scrub, rocky hillsides, trails"},"mo":[3,4,5,6,7,8,9,10],"pk":[],"hp":"Eriogonum, Lotus, Astragalus","elev":"foot,mid"},{"id":"av3","cn":"Behr's Metalmark","sn":"Apodemia virgulti","fam":"Riodinidae","st":"common","desc":"LA County's second metalmark (alongside Mormon). Smaller, darker, more common in warm desert-edge habitats. Tight buckwheat association.","fm":{"Wingspan":"⅔ in–1 in","Upperside":"Dark brown-black with white spots in regular rows; metallic scales","Underside":"Gray-brown with white spots and metallic silver scaling","Flight Period":"Mar–Oct; 2+ broods","Host Plants":"Eriogonum fasciculatum (California buckwheat)","Habitat":"Coastal sage scrub, desert scrub, chaparral — warm rocky slopes with buckwheat"},"mo":[3,4,5,6,7,8,9,10],"pk":[],"hp":"Eriogonum fasciculatum (California buckwheat)","elev":"foot,mid"},{"id":"ba2","cn":"White Checkered-Skipper","sn":"Burnsius albezens","fam":"Hesperiidae","st":"common","desc":"The correct iNat-current name for the white checkered-skipper in SoCal. Paler than Common Checkered-Skipper. 702 LA County obs","fm":{"Wingspan":"¾ in–1 in","Upperside":"Pale gray-white with sparse dark checkering; ♂ blue-gray hairs fresh","Underside":"Nearly white with faint olive-tan bands","Flight Period":"Year-round; multiple broods","Host Plants":"Malvaceae — Sphaeralcea, Malva","Habitat":"Desert washes, arid scrub, open disturbed ground"},"mo":[1,2,3,4,5,6,7,8,9,10,11,12],"pk":[],"hp":"Malvaceae — Sphaeralcea, Malva","elev":"low,foot"},{"id":"eb2","cn":"Bernardino Blue","sn":"Euphilotes bernardino","fam":"Lycaenidae","st":"common","desc":"A buckwheat-specialist blue. Distinguished from Square-spotted Blue by range and subtle underside pattern differences.","fm":{"Wingspan":"⅔ in–1 in","Upperside":"Blue (♂); brown (♀)","Underside":"Gray with black spots; orange HW marginal band","Flight Period":"May–Sep; single brood, sync with buckwheat bloom","Host Plants":"Eriogonum — flowers only","Habitat":"Coastal sage scrub, chaparral slopes with buckwheat"},"mo":[5,6,7,8,9],"pk":[],"hp":"Eriogonum — flowers only","elev":"foot,mid"},{"id":"cn3","cn":"Fatal Metalmark","sn":"Calephelis nemesis","fam":"Riodinidae","st":"common","desc":"LA County's third metalmark — associated with Baccharis in riparian and desert wash habitats. \"Fatal\" name from original description, not toxicity.","fm":{"Wingspan":"⅔ in–1 in","Upperside":"Dark brown with darker median bands; metallic silver-gray spots","Underside":"Orange-brown with metallic silver spots","Flight Period":"Year-round in warm areas; multiple broods","Host Plants":"Baccharis sarothroides (desert broom), B. salicifolia","Habitat":"Desert washes, riparian edges with Baccharis"},"mo":[1,2,3,4,5,6,7,8,9,10,11,12],"pk":[],"hp":"Baccharis sarothroides (desert broom), B. salicifolia","elev":"low,foot"},{"id":"ea3","cn":"El Segundo Blue","sn":"Euphilotes allyni","fam":"Lycaenidae","st":"endangered","desc":"Federally Endangered. Restricted to remnant coastal dune habitat at LAX and nearby sites. One of the rarest butterflies in North America. iNat name differs from our previous entry — updating. (mostly from managed habitat).","fm":{"Wingspan":"⅔ in–¾ in","Upperside":"Blue (♂); brown (♀)","Underside":"Gray with prominent black spots; orange marginal band","Flight Period":"Jun–Aug; single brood, sync with coast buckwheat","Host Plants":"Eriogonum parvifolium (coast buckwheat) — obligate","Habitat":"Coastal dune scrub — El Segundo dunes, LAX area"},"mo":[6,7,8],"pk":[7],"hp":"Eriogonum parvifolium (coast buckwheat) — obligate","elev":"coast"},{"id":"pv01","cn":"Palos Verdes Blue","sn":"Glaucopsyche lygdamus palosverdesensis","fam":"Lycaenidae","st":"endangered","ssp":true,"desc":"Federally Endangered. Once thought extinct, rediscovered 1994. Restricted to coastal sage scrub on Palos Verdes Peninsula — one of the rarest butterflies in the world. Captive breeding program ongoing. LA County endemic.","fm":{"Wingspan":"1 in","Upperside":"♂: silvery-blue with narrow black border. ♀: brownish-gray.","Underside":"Gray with dark spots ringed in white","Flight Period":"Jan–Mar (early); single brood","Host Plants":"Astragalus trichopodus var. lonchus, Acmispon glaber (deerweed)","Habitat":"Coastal sage scrub — Palos Verdes Peninsula only"},"mo":[1,2,3],"pk":[],"hp":"Astragalus trichopodus var. lonchus, Acmispon glaber (deerweed)","elev":"coast"},{"id":"cg3","cn":"Gabb's Checkerspot","sn":"Chlosyne gabbii","fam":"Nymphalidae","st":"common","desc":"Orange-and-black checkerspot of chaparral. Named for William Gabb, California geological surveyor. Closely tied to Hazardia squarrosa host plant.","fm":{"Wingspan":"1–1.5 in","Upperside":"Orange with black markings; cream spots near margins","Underside":"Cream/yellow with orange and black patterning","Flight Period":"Apr–Jun; single brood","Host Plants":"Hazardia squarrosa (saw-toothed goldenbush)","Habitat":"Coastal sage scrub, chaparral, rocky hillsides"},"mo":[4,5,6],"pk":[],"hp":"Hazardia squarrosa (saw-toothed goldenbush)","elev":"foot,mid"},{"id":"ct4","cn":"Common Ringlet","sn":"Coenonympha california","fam":"Nymphalidae","st":"uncommon","desc":"iNat-current name for the California population (split from C. tullia). Small bouncy satyr of grasslands and mountain meadows.","fm":{"Wingspan":"1–1.5 in","Upperside":"Plain tawny-orange","Underside":"Olive-tan with small silver-pupiled eyespot; gray hindwing","Flight Period":"Apr–Aug; single brood","Host Plants":"Poaceae — native grasses","Habitat":"Mountain meadows, grasslands, grassy openings"},"mo":[4,5,6,7,8],"pk":[],"hp":"Poaceae — native grasses","elev":"foot,mid"},{"id":"pe2","cn":"Wandering Skipper","sn":"Panoquina errans","fam":"Hesperiidae","st":"uncommon","desc":"A coastal salt marsh specialist — one of the most habitat-restricted skippers in California. Brown with faint pale spots. Strong flier that wanders from marsh habitat.","fm":{"Wingspan":"1–1.5 in","Upperside":"Dark brown with faint pale forewing spots","Underside":"Brown with faint purplish sheen; pale vein streaks","Flight Period":"Jun–Oct; 1–2 broods","Host Plants":"Distichlis spicata (saltgrass) — obligate","Habitat":"Coastal salt marshes — Ballona Wetlands, Malibu Lagoon, other remnant marshes"},"mo":[6,7,8,9,10],"pk":[],"hp":"Distichlis spicata (saltgrass) — obligate","elev":"coast"},{"id":"pa5","cn":"Large Orange Sulphur","sn":"Phoebis agarithe","fam":"Pieridae","st":"uncommon","desc":"A Neotropical sulphur reaching LA County. Larger and more orange than Cloudless Sulphur. Irregular vagrant/colonizer.","fm":{"Wingspan":"2–3 in","Upperside":"♂: deep orange with subtle darker margins. ♀: paler, yellow-orange.","Underside":"Yellow-orange with small reddish cell spots","Flight Period":"Jun–Nov; immigrant","Host Plants":"Fabaceae — Cassia, Pithecellobium","Habitat":"Gardens, open areas during immigration years"},"mo":[6,7,8,9,10,11],"pk":[],"hp":"Fabaceae: Pithecellobium, Senna (non-native)","elev":"low"},{"id":"ta1","cn":"Tailed Copper","sn":"Tharsalea arota","fam":"Lycaenidae","st":"uncommon","desc":"iNat-current genus (Tharsalea, moved from Lycaena). Copper-orange with delicate hindwing tail. Associated with Ribes in mountain chaparral.","fm":{"Wingspan":"1 in","Upperside":"♂: bright copper-orange. ♀: brown with orange highlights.","Underside":"Gray-white with black spots; thin hindwing tail","Flight Period":"May–Aug; single brood","Host Plants":"Ribes (gooseberries, currants)","Habitat":"Mountain chaparral, oak woodland with Ribes understory"},"mo":[5,6,7,8],"pk":[],"hp":"Ribes (gooseberries, currants)","elev":"foot,mid"},{"id":"sa2","cn":"Avalon Scrub-Hairstreak","sn":"Strymon avalona","fam":"Lycaenidae","st":"rare","desc":"Catalina Island endemic — one of the most geographically restricted butterflies in North America. Gray with blue hindwing scaling. Deerweed specialist. (mostly Catalina).","fm":{"Wingspan":"¾ in–1 in","Upperside":"Gray with blue-purple tint, especially ♂","Underside":"Pale gray; dark postmedian line; small orange/black HW spots near tail","Flight Period":"Feb–Oct; multiple broods","Host Plants":"Acmispon glaber (deerweed) — near-obligate","Habitat":"Coastal sage scrub on Santa Catalina Island (LA County)"},"mo":[2,3,4,5,6,7,8,9,10],"pk":[],"hp":"Acmispon glaber (deerweed) — near-obligate","elev":"coast"},{"id":"en2","cn":"Sleepy Orange","sn":"Abaeis nicippe","fam":"Pieridae","st":"uncommon","desc":"iNat-current name (moved from Abaeis). Bright orange Pierid of warm lowlands. \"Sleepy\" from closed-eye forewing mark.","fm":{"Wingspan":"1.5–2 in","Upperside":"Bright orange with irregular black borders","Underside":"Seasonally variable — yellow (summer) to brick-red (winter)","Flight Period":"Year-round; peaks summer–fall","Host Plants":"Fabaceae — Senna, Cassia","Habitat":"Desert washes, warm open areas, urban edges"},"mo":[1,2,3,4,5,6,7,8,9,10,11,12],"pk":[],"hp":"Fabaceae — Senna, Cassia","elev":"low,foot"},{"id":"pb1","cn":"Becker's White","sn":"Pontia beckerii","fam":"Pieridae","st":"uncommon","desc":"A large, boldly marked white of desert-edge habitats. Green marbling on HW underside heavier than Checkered White. Desert-adapted.","fm":{"Wingspan":"1.5–2 in","Upperside":"White with heavy dark markings especially in ♀; greenish tint fresh","Underside":"HW heavily marbled with yellow-green (bolder than Checkered White)","Flight Period":"Mar–Oct; multiple broods in desert","Host Plants":"Brassicaceae — Stanleya pinnata (prince's plume), Descurainia","Habitat":"Desert washes, alkaline flats, desert-edge with Brassicaceae"},"mo":[3,4,5,6,7,8,9,10],"pk":[],"hp":"Brassicaceae — Stanleya pinnata (prince's plume), Descurainia","elev":"low,foot"},{"id":"tg1","cn":"Gorgon Copper","sn":"Tharsalea gorgon","fam":"Lycaenidae","st":"uncommon","desc":"iNat genus update (Tharsalea). Large copper on buckwheat.","fm":{"Wingspan":"1–1.5 in","Upperside":"♂: bright copper with dark spots. ♀: brown-orange with heavy spotting.","Underside":"Gray-tan with black spots; orange HW marginal band","Flight Period":"Apr–Jul; single brood","Host Plants":"Eriogonum fasciculatum","Habitat":"Coastal sage scrub, chaparral with buckwheat"},"mo":[4,5,6,7],"pk":[],"hp":"Eriogonum fasciculatum","elev":"foot,mid"},{"id":"pp7","cn":"Field Crescent","sn":"Phyciodes pulchella","fam":"Nymphalidae","st":"uncommon","desc":"A mountain crescent similar to Mylitta but typically at higher elevations with Aster host plants (not thistles).","fm":{"Wingspan":"1–1.5 in","Upperside":"Orange with black reticulation; broader dark markings than Mylitta","Underside":"Cream/yellow with brown patch; pattern more contrasting than Mylitta","Flight Period":"May–Aug; 1–2 broods","Host Plants":"Asteraceae — Aster, Erigeron (not Cirsium)","Habitat":"Mountain meadows, forest openings above 4,000'"},"mo":[5,6,7,8],"pk":[],"hp":"Asteraceae — Aster, Erigeron (not Cirsium)","elev":"foot,mid"},{"id":"in1","cn":"Veined Blue","sn":"Icaricia neurona","fam":"Lycaenidae","st":"uncommon","desc":"iNat-current genus. High San Gabriel Mountains endemic — one of LA County's rarest residents. Associated with grape soda lupine above 7,000'.","fm":{"Wingspan":"¾ in–1 in","Upperside":"Blue (♂); brown (♀)","Underside":"Gray with dark spots; veined appearance","Flight Period":"Jun–Aug; single brood","Host Plants":"Lupinus excubitus (grape soda lupine)","Habitat":"High San Gabriel Mtns above 7,000' — extremely restricted"},"mo":[6,7,8],"pk":[],"hp":"Lupinus excubitus (grape soda lupine)","elev":"foot,mid"},{"id":"tx1","cn":"Great Copper","sn":"Tharsalea xanthoides","fam":"Lycaenidae","st":"uncommon","desc":"The largest NA copper — almost hairstreak-sized. Distinctive pale underside with large black spots. Dock specialist.","fm":{"Wingspan":"1.5 in (largest NA copper)","Upperside":"♂: gray with orange submarginal spots. ♀: orange with dark spots.","Underside":"White/cream with bold round black spots; orange submarginal HW band","Flight Period":"May–Jul; single brood","Host Plants":"Rumex (docks) — especially R. hymenosepalus","Habitat":"Moist meadows, streambanks, agricultural edges with dock"},"mo":[5,6,7],"pk":[],"hp":"Rumex (docks) — especially R. hymenosepalus","elev":"low,foot"},{"id":"ca3","cn":"Sagebrush Checkerspot","sn":"Chlosyne acastus","fam":"Nymphalidae","st":"uncommon","desc":"Desert/sagebrush checkerspot. Orange and black with cream spots. Desert edge and Mojave.","fm":{"Wingspan":"1–1.5 in","Upperside":"Orange with black markings; cream marginal spots","Underside":"Cream with orange bands and black outlines","Flight Period":"Apr–Jun; single brood","Host Plants":"Castilleja, Eriodictyon","Habitat":"Desert scrub, sagebrush, arid hillsides"},"mo":[4,5,6],"pk":[],"hp":"Castilleja, Eriodictyon","elev":"foot,mid"},{"id":"il1","cn":"Lupine Blue","sn":"Icaricia lupini","fam":"Lycaenidae","st":"uncommon","desc":"iNat-current genus. Higher elevation than Acmon with broader orange band. Lupine specialist.","fm":{"Wingspan":"⅔ in–1 in","Upperside":"Blue (♂); brown with broader orange band (♀)","Underside":"Like Acmon but orange band broader","Flight Period":"Apr–Jul; 1–2 broods","Host Plants":"Lupinus, Astragalus","Habitat":"Mountain meadows, pine forest clearings"},"mo":[4,5,6,7],"pk":[],"hp":"Lupinus, Astragalus","elev":"foot,mid"},{"id":"hc2","cn":"Western Branded Skipper","sn":"Hesperia colorado","fam":"Hesperiidae","st":"rare","desc":"A mountain grassland skipper with prominent chevron spots on greenish underside.","fm":{"Wingspan":"1–1.5 in","Upperside":"Tawny-orange (♂); brown (♀)","Underside":"Olive-green with pale chevron spot-band","Flight Period":"Jun–Sep; single brood","Host Plants":"Native bunchgrasses — Stipa, Festuca","Habitat":"Mountain meadows, grasslands above 5,000'"},"mo":[6,7,8,9],"pk":[],"hp":"Native bunchgrasses — Stipa, Festuca","elev":"mid,high"},{"id":"ac6","cn":"Desert Orangetip","sn":"Anthocharis cethura","fam":"Pieridae","st":"rare","desc":"A desert spring ephemeral. Vivid orange tips like Sara Orangetip but with more yellow-tinted underside.","fm":{"Wingspan":"1–1.5 in","Upperside":"White/yellow with orange FW tips (♂); reduced (♀)","Underside":"HW marbled green on yellow ground (more yellow than Sara)","Flight Period":"Feb–Apr; single early brood","Host Plants":"Brassicaceae — desert mustards, Caulanthus","Habitat":"Desert washes, desert scrub, Joshua tree woodland"},"mo":[2,3,4],"pk":[],"hp":"Brassicaceae — desert mustards, Caulanthus","elev":"low,foot"},{"id":"ac7","cn":"Callippe Fritillary","sn":"Argynnis callippe","fam":"Nymphalidae","st":"rare","desc":"iNat-current genus (Argynnis, moved from Speyeria). Montane fritillary.","fm":{"Wingspan":"2–2.5 in","Upperside":"Tawny orange; black spots and bars","Underside":"Olive-brown with smaller silver spots","Flight Period":"May–Aug; single brood","Host Plants":"Viola pedunculata (Johnny-jump-up)","Habitat":"Grasslands, chaparral openings"},"mo":[5,6,7,8],"pk":[],"hp":"Viola pedunculata (Johnny-jump-up)","elev":"foot,mid"},{"id":"hg1","cn":"Golden Hairstreak","sn":"Habrodais grunus","fam":"Lycaenidae","st":"rare","desc":"Unusual hairstreak — golden-brown rather than gray. Associated with canyon live oak at mid-elevations. Single-brooded.","fm":{"Wingspan":"1 in","Upperside":"Golden-brown; smooth unmarked","Underside":"Golden-tan with faint darker postmedian line; no tails","Flight Period":"Jun–Aug; single brood","Host Plants":"Quercus chrysolepis (canyon live oak) — near-obligate","Habitat":"Canyon live oak woodland, rocky canyon slopes"},"mo":[6,7,8],"pk":[],"hp":"Quercus chrysolepis (canyon live oak) — near-obligate","elev":"foot,mid"},{"id":"em2","cn":"Mojave Blue","sn":"Euphilotes mojave","fam":"Lycaenidae","st":"rare","desc":"Desert buckwheat specialist. Distinguished from Bernardino by range (Mojave side) and minor pattern differences.","fm":{"Wingspan":"⅔ in–¾ in","Upperside":"Blue (♂); brown (♀)","Underside":"Gray; orange HW band; spots slightly different from bernardino","Flight Period":"May–Jul; single brood","Host Plants":"Eriogonum — desert species","Habitat":"Mojave desert scrub with Eriogonum"},"mo":[5,6,7],"pk":[],"hp":"Eriogonum — desert species","elev":"low,foot"},{"id":"ac8","cn":"Coronis Fritillary","sn":"Argynnis coronis","fam":"Nymphalidae","st":"rare","desc":"iNat-current genus. Large orange fritillary with silver spots. Mountain meadows.","fm":{"Wingspan":"2–3 in","Upperside":"Orange with dark spots; black veins","Underside":"HW with prominent silver spots on greenish-brown ground","Flight Period":"Jun–Sep; single brood","Host Plants":"Viola (violets)","Habitat":"Mountain meadows, moist canyons above 4,000'"},"mo":[6,7,8,9],"pk":[],"hp":"Viola (violets)","elev":"foot,mid"},{"id":"lc2","cn":"American Snout","sn":"Libytheana carinenta","fam":"Nymphalidae","st":"rare","desc":"Unmistakable — elongated palps form a \"snout.\" Orange-and-brown pattern. Hackberry specialist. Rare in LA County — mostly desert edge.","fm":{"Wingspan":"1.5–2 in","Upperside":"Brown with orange patches; elongated snout-like palps (diagnostic)","Underside":"Gray-brown; leaf-like camouflage when closed","Flight Period":"Year-round in tropics; vagrant to LA","Host Plants":"Celtis (hackberry)","Habitat":"Riparian with hackberry; desert washes"},"mo":[1,2,3,4,5,6,7,8,9,10,11,12],"pk":[],"hp":"Cannabaceae: Celtis reticulata (netleaf hackberry)","elev":"low,foot"},{"id":"hc3","cn":"Zebra Longwing","sn":"Heliconius charithonia","fam":"Nymphalidae","st":"rare","desc":"Neotropical. Long narrow wings with bold black and yellow stripes. Communal rooster. Occasional vagrant to SoCal — may establish in warm years with Passiflora.","fm":{"Wingspan":"3–4 in","Upperside":"Black with bold yellow stripes","Underside":"Similar with red basal spots","Flight Period":"Year-round in tropics; vagrant to LA summer–fall","Host Plants":"Passiflora","Habitat":"Gardens with passionvine during vagrant events"},"mo":[1,2,3,4,5,6,7,8,9,10,11,12],"pk":[],"hp":"Passiflora","elev":"low"},{"id":"sb6","cn":"Behr's Hairstreak","sn":"Satyrium behrii","fam":"Lycaenidae","st":"rare","desc":"A small gray-green hairstreak of desert-edge habitats with antelope brush. Rare at western range edge.","fm":{"Wingspan":"¾ in–1 in","Upperside":"Gray-brown","Underside":"Gray-green with thin white postmedian line; small orange spot near tail","Flight Period":"Jun–Jul; single brood","Host Plants":"Purshia tridentata (antelope bitterbrush)","Habitat":"Desert-edge sagebrush/bitterbrush communities"},"mo":[6,7],"pk":[],"hp":"Purshia tridentata (antelope bitterbrush)","elev":"mid,high"},{"id":"hj1","cn":"Juba Skipper","sn":"Hesperia juba","fam":"Hesperiidae","st":"rare","desc":"A montane branded skipper with jagged/angular greenish HW spots below.","fm":{"Wingspan":"1–1.5 in","Upperside":"Tawny-orange (♂); brown (♀)","Underside":"Olive-green with large jagged/angular white spots","Flight Period":"May–Sep; 1–2 broods","Host Plants":"Poaceae — Stipa, Festuca, Elymus","Habitat":"Mountain meadows, open conifer woodland"},"mo":[5,6,7,8,9],"pk":[],"hp":"Poaceae — Stipa, Festuca, Elymus","elev":"foot,mid,high"},{"id":"ch2","cn":"Harford's Sulphur","sn":"Colias harfordii","fam":"Pieridae","st":"vagrant","desc":"A California endemic sulphur. Orange (♂) or white (♀). Associated with Astragalus. Very rare in LA County.","fm":{"Wingspan":"1.5–2 in","Upperside":"♂: bright orange with dark borders. ♀: white/yellow.","Underside":"Greenish-yellow with pink-rimmed cell spot","Flight Period":"May–Jul; single brood","Host Plants":"Astragalus spp.","Habitat":"Mountain meadows; vagrant to LA lowlands"},"mo":[5,6,7],"pk":[],"hp":"Fabaceae: Astragalus spp., Acmispon spp.","elev":"mid,high"},{"id":"el3","cn":"Desert Marble","sn":"Euchloe lotta","fam":"Pieridae","st":"vagrant","desc":"Desert spring white. Bold green marbling on underside. Very early spring flier in desert canyons.","fm":{"Wingspan":"1–1.5 in","Upperside":"White; black discal spot on FW","Underside":"HW with bold irregular green marble pattern on white","Flight Period":"Feb–Apr; single early brood","Host Plants":"Brassicaceae — desert mustards","Habitat":"Desert washes, rocky desert canyons"},"mo":[2,3,4],"pk":[],"hp":"Brassicaceae — desert mustards","elev":"foot,mid"},{"id":"ep5","cn":"Pallid Blue","sn":"Euphilotes pallescens","fam":"Lycaenidae","st":"vagrant","desc":"Very pale buckwheat specialist. Extremely local.","fm":{"Wingspan":"⅔ in–¾ in","Upperside":"Pale blue (♂); pale brown (♀)","Underside":"Very pale gray; reduced spotting","Flight Period":"May–Jul","Host Plants":"Eriogonum — specific desert species","Habitat":"Desert buckwheat sites"},"mo":[5,6,7],"pk":[],"hp":"Eriogonum — specific desert species","elev":"low,foot"},{"id":"cp2","cn":"Northern Cloudywing","sn":"Cecropterus pylades","fam":"Hesperiidae","st":"vagrant","desc":"A dark, robust spread-wing skipper. White FW spots aligned in an arc. Very rare in LA.","fm":{"Wingspan":"1–1.5 in","Upperside":"Dark brown with aligned white FW spots in an arc","Underside":"Dark brown with faint pale bands","Flight Period":"Apr–Jul","Host Plants":"Fabaceae — Lathyrus, Trifolium, Desmodium","Habitat":"Woodland edges; vagrant to LA"},"mo":[4,5,6,7],"pk":[],"hp":"Fabaceae — Lathyrus, Trifolium, Desmodium","elev":"low,foot"},{"id":"pd4","cn":"Lime Swallowtail","sn":"Papilio demoleus","fam":"Papilionidae","st":"vagrant","desc":"Old World citrus pest swallowtail — NOT native. Three LA records may represent accidental importation on citrus shipments or deliberate releases. Invasive threat if established.","fm":{"Wingspan":"3–4 in","Upperside":"Black/brown with scattered yellow spots (not banded like native swallowtails)","Underside":"Yellow with blue and red HW spots","Flight Period":"Year-round in tropics","Host Plants":"Rutaceae — Citrus (major pest in Old World)","Habitat":"Non-native — likely accidental/imported. Report sightings."},"mo":[1,2,3,4,5,6,7,8,9,10,11,12],"pk":[],"hp":"Rutaceae — Citrus (major pest in Old World)","elev":"low"},{"id":"zc1","cn":"Southern Dogface","sn":"Zerene cesonia","fam":"Pieridae","st":"vagrant","desc":"iNat-current name (moved from Colias). Similar to CA Dogface but smaller.","fm":{"Wingspan":"1.5–2 in","Upperside":"♂: yellow with dark \"dogface\" outline. ♀: yellow-green.","Underside":"Greenish-yellow; pink cell spot","Flight Period":"Mar–Nov; multiple broods","Host Plants":"Dalea, Amorpha, Trifolium","Habitat":"Desert washes, dry grasslands"},"mo":[3,4,5,6,7,8,9,10,11],"pk":[],"hp":"Dalea, Amorpha, Trifolium","elev":"low,foot"},{"id":"ps7","cn":"Alkali Skipper","sn":"Pseudocopaeodes eunus","fam":"Hesperiidae","st":"vagrant","desc":"A tiny skipper of alkaline desert flats. Extremely local.","fm":{"Wingspan":"⅔ in–1 in","Upperside":"Pale orange-yellow; narrow dark borders","Underside":"Pale yellow; unmarked or faint veining","Flight Period":"May–Sep; 2 broods","Host Plants":"Distichlis spicata (saltgrass)","Habitat":"Alkaline desert flats, salt marshes"},"mo":[5,6,7,8,9],"pk":[],"hp":"Distichlis spicata (saltgrass)","elev":"low,foot"},{"id":"cc2","cn":"California Patch","sn":"Chlosyne californica","fam":"Nymphalidae","st":"vagrant","desc":"Desert checkerspot. Bold orange/cream/black pattern. — extreme vagrant from desert.","fm":{"Wingspan":"1.5 in","Upperside":"Bold orange and cream patches on black ground","Underside":"Cream with orange and black pattern","Flight Period":"Year-round in desert; multiple broods","Host Plants":"Ambrosia, Viguiera","Habitat":"Sonoran desert scrub; vagrant to LA basin"},"mo":[1,2,3,4,5,6,7,8,9,10,11,12],"pk":[],"hp":"Ambrosia, Viguiera","elev":"low,foot"},{"id":"bp4","cn":"Polydamas Swallowtail","sn":"Battus polydamas","fam":"Papilionidae","st":"vagrant","desc":"A tailless Neotropical swallowtail. Gold-edged black wings. Extremely rare vagrant to LA.","fm":{"Wingspan":"3–4 in","Upperside":"Black with gold/yellow submarginal band; no tails","Underside":"Black with red basal spots; gold band","Flight Period":"Year-round in tropics","Host Plants":"Aristolochia (pipevines)","Habitat":"Tropical; extreme vagrant to SoCal"},"mo":[1,2,3,4,5,6,7,8,9,10,11,12],"pk":[],"hp":"Aristolochia (pipevines)","elev":"low"},{"id":"cm4","cn":"Moss's Elfin","sn":"Callophrys mossii","fam":"Lycaenidae","st":"vagrant","desc":"A small elfin of rocky habitats with stonecrop. Very localized.","fm":{"Wingspan":"⅔ in–1 in","Upperside":"Brown","Underside":"Reddish-brown basally; frosted gray outwardly; jagged line between","Flight Period":"Feb–May; single brood","Host Plants":"Sedum (stonecrop)","Habitat":"Rocky outcrops with Sedum"},"mo":[2,3,4,5],"pk":[],"hp":"Sedum (stonecrop)","elev":"low,foot"},{"id":"si1","cn":"Mallow Scrub-Hairstreak","sn":"Strymon istapa","fam":"Lycaenidae","st":"vagrant","desc":"Subtropical hairstreak at extreme range edge.","fm":{"Wingspan":"⅔ in–1 in","Upperside":"Gray-brown","Underside":"Pale gray; dark postmedian line; small spots","Flight Period":"Mar–Nov","Host Plants":"Malvaceae — Sida, Abutilon","Habitat":"Warm desert edges with Malvaceae"},"mo":[3,4,5,6,7,8,9,10,11],"pk":[],"hp":"Malvaceae — Sida, Abutilon","elev":"low,foot"},{"id":"cs4","cn":"Silver-banded Hairstreak","sn":"Chlorostrymon simaethis","fam":"Lycaenidae","st":"vagrant","desc":"Tiny tropical hairstreak. Brilliant green underside.","fm":{"Wingspan":"⅔ in–¾ in","Upperside":"Dark with purple sheen (♂)","Underside":"Brilliant green; silver-white postmedian band","Flight Period":"Year-round in tropics","Host Plants":"Fabaceae — Pithecellobium, balloon vine","Habitat":"Tropical; extreme vagrant"},"mo":[1,2,3,4,5,6,7,8,9,10,11,12],"pk":[],"hp":"Fabaceae — Pithecellobium, balloon vine","elev":"low,foot"},{"id":"my2","cn":"Yucca Giant-Skipper","sn":"Megathymus yuccae","fam":"Hesperiidae","st":"vagrant","desc":"Large, dark skipper whose larvae bore inside living yucca stalks.","fm":{"Wingspan":"1.5–2.5 in","Upperside":"Dark brown-black with yellow FW spots and narrow yellow HW border","Underside":"Dark with frosted gray overscaling","Flight Period":"Feb–May; single brood","Host Plants":"Yucca spp. — larvae bore in living root crown","Habitat":"Desert yucca grasslands, Joshua tree woodland"},"mo":[2,3,4,5],"pk":[],"hp":"Yucca spp. — larvae bore in living root crown","elev":"low,foot"},{"id":"os1","cn":"Santa Cruz Skipper","sn":"Ochlodes santacruza","fam":"Hesperiidae","st":"vagrant","desc":"Recently described/split species. Similar to Woodland Skipper. Taxonomy still being resolved.","fm":{"Wingspan":"1 in","Upperside":"Tawny-orange","Underside":"Pale yellow-orange with spot-band","Flight Period":"Jul–Sep","Host Plants":"Poaceae","Habitat":"Coastal scrub, woodland edges"},"mo":[7,8,9],"pk":[],"hp":"Poaceae","elev":"coast"},{"id":"aj2","cn":"White Peacock","sn":"Anartia jatrophae","fam":"Nymphalidae","st":"vagrant","desc":"Tropical nymphalid with pale white wings and orange margins. Single LA County obs— extreme vagrant. Establishing in south Florida/Texas.","fm":{"Wingspan":"2–2.5 in","Upperside":"White with small brown spots; orange HW margin and eyespot","Underside":"Similar but paler","Flight Period":"Year-round in tropics","Host Plants":"Acanthaceae — Ruellia, Blechum","Habitat":"Tropical wetlands; extreme vagrant to LA"},"mo":[1,2,3,4,5,6,7,8,9,10,11,12],"pk":[],"hp":"Acanthaceae — Ruellia, Blechum","elev":"low,foot"},{"id":"la3","cn":"Viceroy","sn":"Limenitis archippus","fam":"Nymphalidae","st":"vagrant","desc":"Famous Monarch mimic. Not a regular LA County resident — single obslikely a stray. Distinguished from Monarch by black postmedian HW line.","fm":{"Wingspan":"2–3 in","Upperside":"Orange with black veins (like Monarch) PLUS black postmedian HW line (diagnostic)","Underside":"Like Monarch but with black HW crossline","Flight Period":"May–Sep","Host Plants":"Salix, Populus — willows and cottonwoods","Habitat":"Riparian woodland; extreme vagrant to LA"},"mo":[5,6,7,8,9],"pk":[],"hp":"Salix, Populus — willows and cottonwoods","elev":"low,foot,mid"},{"id":"pp8","cn":"Orange-barred Sulphur","sn":"Phoebis philea","fam":"Pieridae","st":"vagrant","desc":"Large bright orange Neotropical sulphur. Single LA obs— extreme vagrant.","fm":{"Wingspan":"2.5–3 in","Upperside":"♂: bright orange with orange bar. ♀: yellow with pink-orange patches.","Underside":"Yellow with pink/red cell spots","Flight Period":"Year-round in tropics","Host Plants":"Fabaceae — Cassia, Senna","Habitat":"Tropical; extreme vagrant to LA"},"mo":[1,2,3,4,5,6,7,8,9,10,11,12],"pk":[],"hp":"Fabaceae — Cassia, Senna","elev":"low,foot"},{"id":"pe3","cn":"San Emigdio Blue","sn":"Plebulina emigdionis","fam":"Lycaenidae","st":"vagrant","desc":"iNat-current genus (Plebulina). Desert-edge alkali specialist. under this name.","fm":{"Wingspan":"⅔ in–1 in","Upperside":"Blue (♂); brown (♀)","Underside":"White with black dots; no orange band","Flight Period":"Mar–May; single brood","Host Plants":"Astragalus (desert species)","Habitat":"Alkaline flats, desert edges"},"mo":[3,4,5],"pk":[],"hp":"Astragalus (desert species)","elev":"low,foot"},{"id":"oa1","cn":"Orange Skipperling","sn":"Copaeodes aurantiaca","fam":"Hesperiidae","st":"vagrant","desc":"iNat-current genus. Tiny unmarked orange skipper.","fm":{"Wingspan":"⅔ in–¾ in","Upperside":"Bright unmarked orange","Underside":"Orange, unmarked","Flight Period":"Apr–Oct","Host Plants":"Bermuda, Cynodon","Habitat":"Desert washes, dry grasslands"},"mo":[4,5,6,7,8,9,10],"pk":[],"hp":"Bermuda, Cynodon","elev":"low,foot"}]